<?xml version="1.0" encoding="UTF-8"?>
<!DOCTYPE plist PUBLIC "-//Apple Computer//DTD PLIST 1.0//EN" "http://www.apple.com/DTDs/PropertyList-1.0.dtd">
<plist version="1.0">
<dict>
	<key>Tracks</key>
	<dict>
		<key>35377</key>
		<dict>
			<key>Track ID</key><integer>35377</integer>
			<key>Size</key><integer>5263950</integer>
			<key>Total Time</key><integer>218200</integer>
			<key>Track Number</key><integer>5</integer>
			<key>Track Count</key><integer>17</integer>
			<key>Date Modified</key><date>2013-10-19T04:11:20Z</date>
			<key>Date Added</key><date>2018-04-09T14:48:31Z</date>
			<key>Bit Rate</key><integer>192</integer>
			<key>Sample Rate</key><integer>44100</integer>
			<key>Compilation</key><true/>
			<key>Artwork Count</key><integer>1</integer>
			<key>Persistent ID</key><string>2B26709E1FB8B5FA</string>
			<key>Track Type</key><string>File</string>
			<key>File Folder Count</key><integer>5</integer>
			<key>Library Folder Count</key><integer>1</integer>
			<key>Name</key><string>Paradox</string>
			<key>Artist</key><string>Thierry Meyer</string>
			<key>Album</key><string>Systems of Romance Vol. 1</string>
			<key>Genre</key><string>Coldwave</string>
			<key>Kind</key><string>MPEG audio file</string>
			<key>Location</key><string>file:///Users/tonyfischetti/Music/iTunes/iTunes%20Media/Music/Compilations/Systems%20of%20Romance%20Vol.%201/05%20Paradox.mp3</string>
		</dict>
		<key>35375</key>
		<dict>
			<key>Track ID</key><integer>35375</integer>
			<key>Size</key><integer>3971002</integer>
			<key>Total Time</key><integer>164336</integer>
			<key>Track Number</key><integer>6</integer>
			<key>Track Count</key><integer>17</integer>
			<key>Date Modified</key><date>2013-10-19T04:11:20Z</date>
			<key>Date Added</key><date>2018-04-09T14:48:31Z</date>
			<key>Bit Rate</key><integer>192</integer>
			<key>Sample Rate</key><integer>44100</integer>
			<key>Compilation</key><true/>
			<key>Artwork Count</key><integer>1</integer>
			<key>Persistent ID</key><string>E830184A9F342031</string>
			<key>Track Type</key><string>File</string>
			<key>File Folder Count</key><integer>5</integer>
			<key>Library Folder Count</key><integer>1</integer>
			<key>Name</key><string>First Impressions</string>
			<key>Artist</key><string>VHF</string>
			<key>Album</key><string>Systems of Romance Vol. 1</string>
			<key>Genre</key><string>Coldwave</string>
			<key>Kind</key><string>MPEG audio file</string>
			<key>Location</key><string>file:///Users/tonyfischetti/Music/iTunes/iTunes%20Media/Music/Compilations/Systems%20of%20Romance%20Vol.%201/06%20First%20Impressions.mp3</string>
		</dict>
		<key>35393</key>
		<dict>
			<key>Track ID</key><integer>35393</integer>
			<key>Size</key><integer>4343616</integer>
			<key>Total Time</key><integer>179853</integer>
			<key>Track Number</key><integer>7</integer>
			<key>Track Count</key><integer>17</integer>
			<key>Date Modified</key><date>2013-10-19T04:11:20Z</date>
			<key>Date Added</key><date>2018-04-09T14:48:31Z</date>
			<key>Bit Rate</key><integer>192</integer>
			<key>Sample Rate</key><integer>44100</integer>
			<key>Compilation</key><true/>
			<key>Artwork Count</key><integer>1</integer>
			<key>Persistent ID</key><string>079F407535E2615D</string>
			<key>Track Type</key><string>File</string>
			<key>File Folder Count</key><integer>5</integer>
			<key>Library Folder Count</key><integer>1</integer>
			<key>Name</key><string>Tanz Ins Gluck</string>
			<key>Artist</key><string>Die Neue Weltmacht</string>
			<key>Album</key><string>Systems of Romance Vol. 1</string>
			<key>Genre</key><string>Coldwave</string>
			<key>Kind</key><string>MPEG audio file</string>
			<key>Location</key><string>file:///Users/tonyfischetti/Music/iTunes/iTunes%20Media/Music/Compilations/Systems%20of%20Romance%20Vol.%201/07%20Tanz%20Ins%20Gluck.mp3</string>
		</dict>
		<key>35381</key>
		<dict>
			<key>Track ID</key><integer>35381</integer>
			<key>Size</key><integer>7344769</integer>
			<key>Total Time</key><integer>304901</integer>
			<key>Track Number</key><integer>8</integer>
			<key>Track Count</key><integer>17</integer>
			<key>Date Modified</key><date>2013-10-19T04:11:21Z</date>
			<key>Date Added</key><date>2018-04-09T14:48:31Z</date>
			<key>Bit Rate</key><integer>192</integer>
			<key>Sample Rate</key><integer>44100</integer>
			<key>Compilation</key><true/>
			<key>Artwork Count</key><integer>1</integer>
			<key>Persistent ID</key><string>6D13C504790D79B5</string>
			<key>Track Type</key><string>File</string>
			<key>File Folder Count</key><integer>5</integer>
			<key>Library Folder Count</key><integer>1</integer>
			<key>Name</key><string>Bronson</string>
			<key>Artist</key><string>Eirin Peryglus</string>
			<key>Album</key><string>Systems of Romance Vol. 1</string>
			<key>Genre</key><string>Coldwave</string>
			<key>Kind</key><string>MPEG audio file</string>
			<key>Location</key><string>file:///Users/tonyfischetti/Music/iTunes/iTunes%20Media/Music/Compilations/Systems%20of%20Romance%20Vol.%201/08%20Bronson.mp3</string>
		</dict>
		<key>35397</key>
		<dict>
			<key>Track ID</key><integer>35397</integer>
			<key>Size</key><integer>7515305</integer>
			<key>Total Time</key><integer>312006</integer>
			<key>Track Number</key><integer>9</integer>
			<key>Track Count</key><integer>17</integer>
			<key>Date Modified</key><date>2013-10-19T04:11:21Z</date>
			<key>Date Added</key><date>2018-04-09T14:48:31Z</date>
			<key>Bit Rate</key><integer>192</integer>
			<key>Sample Rate</key><integer>44100</integer>
			<key>Compilation</key><true/>
			<key>Artwork Count</key><integer>1</integer>
			<key>Persistent ID</key><string>268E08091610C83E</string>
			<key>Track Type</key><string>File</string>
			<key>File Folder Count</key><integer>5</integer>
			<key>Library Folder Count</key><integer>1</integer>
			<key>Name</key><string>All That Place</string>
			<key>Artist</key><string>Excentrique Noiz</string>
			<key>Album</key><string>Systems of Romance Vol. 1</string>
			<key>Genre</key><string>Coldwave</string>
			<key>Kind</key><string>MPEG audio file</string>
			<key>Location</key><string>file:///Users/tonyfischetti/Music/iTunes/iTunes%20Media/Music/Compilations/Systems%20of%20Romance%20Vol.%201/09%20All%20That%20Place.mp3</string>
		</dict>
		<key>35407</key>
		<dict>
			<key>Track ID</key><integer>35407</integer>
			<key>Size</key><integer>6785542</integer>
			<key>Total Time</key><integer>281600</integer>
			<key>Track Number</key><integer>10</integer>
			<key>Track Count</key><integer>17</integer>
			<key>Date Modified</key><date>2013-10-19T04:11:21Z</date>
			<key>Date Added</key><date>2018-04-09T14:48:31Z</date>
			<key>Bit Rate</key><integer>192</integer>
			<key>Sample Rate</key><integer>44100</integer>
			<key>Compilation</key><true/>
			<key>Artwork Count</key><integer>1</integer>
			<key>Persistent ID</key><string>D7FC987713963C87</string>
			<key>Track Type</key><string>File</string>
			<key>File Folder Count</key><integer>5</integer>
			<key>Library Folder Count</key><integer>1</integer>
			<key>Name</key><string>Secret Affair</string>
			<key>Artist</key><string>Industrie</string>
			<key>Album</key><string>Systems of Romance Vol. 1</string>
			<key>Genre</key><string>Coldwave</string>
			<key>Kind</key><string>MPEG audio file</string>
			<key>Location</key><string>file:///Users/tonyfischetti/Music/iTunes/iTunes%20Media/Music/Compilations/Systems%20of%20Romance%20Vol.%201/10%20Secret%20Affair.mp3</string>
		</dict>
		<key>35401</key>
		<dict>
			<key>Track ID</key><integer>35401</integer>
			<key>Size</key><integer>4874637</integer>
			<key>Total Time</key><integer>201978</integer>
			<key>Track Number</key><integer>11</integer>
			<key>Track Count</key><integer>17</integer>
			<key>Date Modified</key><date>2013-10-19T04:11:21Z</date>
			<key>Date Added</key><date>2018-04-09T14:48:31Z</date>
			<key>Bit Rate</key><integer>192</integer>
			<key>Sample Rate</key><integer>44100</integer>
			<key>Compilation</key><true/>
			<key>Artwork Count</key><integer>1</integer>
			<key>Persistent ID</key><string>8FDF26F57F9E823A</string>
			<key>Track Type</key><string>File</string>
			<key>File Folder Count</key><integer>5</integer>
			<key>Library Folder Count</key><integer>1</integer>
			<key>Name</key><string>The Cops Are Coming</string>
			<key>Artist</key><string>Karnage</string>
			<key>Album</key><string>Systems of Romance Vol. 1</string>
			<key>Genre</key><string>Coldwave</string>
			<key>Kind</key><string>MPEG audio file</string>
			<key>Sort Name</key><string>Cops Are Coming</string>
			<key>Location</key><string>file:///Users/tonyfischetti/Music/iTunes/iTunes%20Media/Music/Compilations/Systems%20of%20Romance%20Vol.%201/11%20The%20Cops%20Are%20Coming.mp3</string>
		</dict>
		<key>35385</key>
		<dict>
			<key>Track ID</key><integer>35385</integer>
			<key>Size</key><integer>4342992</integer>
			<key>Total Time</key><integer>179826</integer>
			<key>Track Number</key><integer>12</integer>
			<key>Track Count</key><integer>17</integer>
			<key>Date Modified</key><date>2013-10-19T04:11:22Z</date>
			<key>Date Added</key><date>2018-04-09T14:48:31Z</date>
			<key>Bit Rate</key><integer>192</integer>
			<key>Sample Rate</key><integer>44100</integer>
			<key>Compilation</key><true/>
			<key>Artwork Count</key><integer>1</integer>
			<key>Persistent ID</key><string>E20E051E62585350</string>
			<key>Track Type</key><string>File</string>
			<key>File Folder Count</key><integer>5</integer>
			<key>Library Folder Count</key><integer>1</integer>
			<key>Name</key><string>Interferon</string>
			<key>Artist</key><string>Phillippe Laurent</string>
			<key>Album</key><string>Systems of Romance Vol. 1</string>
			<key>Genre</key><string>Coldwave</string>
			<key>Kind</key><string>MPEG audio file</string>
			<key>Location</key><string>file:///Users/tonyfischetti/Music/iTunes/iTunes%20Media/Music/Compilations/Systems%20of%20Romance%20Vol.%201/12%20Interferon.mp3</string>
		</dict>
		<key>35389</key>
		<dict>
			<key>Track ID</key><integer>35389</integer>
			<key>Size</key><integer>4266526</integer>
			<key>Total Time</key><integer>176640</integer>
			<key>Track Number</key><integer>13</integer>
			<key>Track Count</key><integer>17</integer>
			<key>Date Modified</key><date>2013-10-19T04:11:22Z</date>
			<key>Date Added</key><date>2018-04-09T14:48:31Z</date>
			<key>Bit Rate</key><integer>192</integer>
			<key>Sample Rate</key><integer>44100</integer>
			<key>Compilation</key><true/>
			<key>Artwork Count</key><integer>1</integer>
			<key>Persistent ID</key><string>4E5BA93FD6D69CC3</string>
			<key>Track Type</key><string>File</string>
			<key>File Folder Count</key><integer>5</integer>
			<key>Library Folder Count</key><integer>1</integer>
			<key>Name</key><string>Mole at the Circus</string>
			<key>Artist</key><string>Slim Bridge &amp; The Wildflowers</string>
			<key>Album</key><string>Systems of Romance Vol. 1</string>
			<key>Genre</key><string>Coldwave</string>
			<key>Kind</key><string>MPEG audio file</string>
			<key>Location</key><string>file:///Users/tonyfischetti/Music/iTunes/iTunes%20Media/Music/Compilations/Systems%20of%20Romance%20Vol.%201/13%20Mole%20at%20the%20Circus.mp3</string>
		</dict>
		<key>35387</key>
		<dict>
			<key>Track ID</key><integer>35387</integer>
			<key>Size</key><integer>6998075</integer>
			<key>Total Time</key><integer>290455</integer>
			<key>Track Number</key><integer>14</integer>
			<key>Track Count</key><integer>17</integer>
			<key>Date Modified</key><date>2013-10-19T04:11:22Z</date>
			<key>Date Added</key><date>2018-04-09T14:48:31Z</date>
			<key>Bit Rate</key><integer>192</integer>
			<key>Sample Rate</key><integer>44100</integer>
			<key>Compilation</key><true/>
			<key>Artwork Count</key><integer>1</integer>
			<key>Persistent ID</key><string>A877110D924C63BB</string>
			<key>Track Type</key><string>File</string>
			<key>File Folder Count</key><integer>5</integer>
			<key>Library Folder Count</key><integer>1</integer>
			<key>Name</key><string>The Time Of Your Life</string>
			<key>Artist</key><string>This Perfect Day</string>
			<key>Album</key><string>Systems of Romance Vol. 1</string>
			<key>Genre</key><string>Coldwave</string>
			<key>Kind</key><string>MPEG audio file</string>
			<key>Sort Name</key><string>Time Of Your Life</string>
			<key>Location</key><string>file:///Users/tonyfischetti/Music/iTunes/iTunes%20Media/Music/Compilations/Systems%20of%20Romance%20Vol.%201/14%20The%20Time%20Of%20Your%20Life.mp3</string>
		</dict>
		<key>35379</key>
		<dict>
			<key>Track ID</key><integer>35379</integer>
			<key>Size</key><integer>5620680</integer>
			<key>Total Time</key><integer>233064</integer>
			<key>Track Number</key><integer>15</integer>
			<key>Track Count</key><integer>17</integer>
			<key>Date Modified</key><date>2013-10-19T04:11:22Z</date>
			<key>Date Added</key><date>2018-04-09T14:48:31Z</date>
			<key>Bit Rate</key><integer>192</integer>
			<key>Sample Rate</key><integer>44100</integer>
			<key>Play Count</key><integer>2</integer>
			<key>Play Date</key><integer>3645355356</integer>
			<key>Play Date UTC</key><date>2019-07-07T18:42:36Z</date>
			<key>Compilation</key><true/>
			<key>Artwork Count</key><integer>1</integer>
			<key>Persistent ID</key><string>5A114F1A33C373B4</string>
			<key>Track Type</key><string>File</string>
			<key>File Folder Count</key><integer>5</integer>
			<key>Library Folder Count</key><integer>1</integer>
			<key>Name</key><string>Trading In Guilt</string>
			<key>Artist</key><string>Vital Signs</string>
			<key>Album</key><string>Systems of Romance Vol. 1</string>
			<key>Genre</key><string>Coldwave</string>
			<key>Kind</key><string>MPEG audio file</string>
			<key>Location</key><string>file:///Users/tonyfischetti/Music/iTunes/iTunes%20Media/Music/Compilations/Systems%20of%20Romance%20Vol.%201/15%20Trading%20In%20Guilt.mp3</string>
		</dict>
		<key>35403</key>
		<dict>
			<key>Track ID</key><integer>35403</integer>
			<key>Size</key><integer>5271490</integer>
			<key>Total Time</key><integer>218514</integer>
			<key>Track Number</key><integer>16</integer>
			<key>Track Count</key><integer>17</integer>
			<key>Date Modified</key><date>2013-10-19T04:11:22Z</date>
			<key>Date Added</key><date>2018-04-09T14:48:31Z</date>
			<key>Bit Rate</key><integer>192</integer>
			<key>Sample Rate</key><integer>44100</integer>
			<key>Compilation</key><true/>
			<key>Artwork Count</key><integer>1</integer>
			<key>Persistent ID</key><string>B82E008965DA84B5</string>
			<key>Track Type</key><string>File</string>
			<key>File Folder Count</key><integer>5</integer>
			<key>Library Folder Count</key><integer>1</integer>
			<key>Name</key><string>Ond Mae'r Dawns Yn Mynd Ymlaen</string>
			<key>Artist</key><string>Y Gwas Gwyr</string>
			<key>Album</key><string>Systems of Romance Vol. 1</string>
			<key>Genre</key><string>Coldwave</string>
			<key>Kind</key><string>MPEG audio file</string>
			<key>Location</key><string>file:///Users/tonyfischetti/Music/iTunes/iTunes%20Media/Music/Compilations/Systems%20of%20Romance%20Vol.%201/16%20Ond%20Mae'r%20Dawns%20Yn%20Mynd%20Ymlaen.mp3</string>
		</dict>
		<key>35391</key>
		<dict>
			<key>Track ID</key><integer>35391</integer>
			<key>Size</key><integer>6621951</integer>
			<key>Total Time</key><integer>274782</integer>
			<key>Track Number</key><integer>17</integer>
			<key>Track Count</key><integer>17</integer>
			<key>Date Modified</key><date>2013-10-19T04:11:23Z</date>
			<key>Date Added</key><date>2018-04-09T14:48:31Z</date>
			<key>Bit Rate</key><integer>192</integer>
			<key>Sample Rate</key><integer>44100</integer>
			<key>Compilation</key><true/>
			<key>Artwork Count</key><integer>1</integer>
			<key>Persistent ID</key><string>FFDF17B49FA2B87A</string>
			<key>Track Type</key><string>File</string>
			<key>File Folder Count</key><integer>5</integer>
			<key>Library Folder Count</key><integer>1</integer>
			<key>Name</key><string>Tell Me When Your Heart Beats</string>
			<key>Artist</key><string>New Scientists</string>
			<key>Album</key><string>Systems of Romance Vol. 1</string>
			<key>Genre</key><string>Coldwave</string>
			<key>Kind</key><string>MPEG audio file</string>
			<key>Location</key><string>file:///Users/tonyfischetti/Music/iTunes/iTunes%20Media/Music/Compilations/Systems%20of%20Romance%20Vol.%201/17%20Tell%20Me%20When%20Your%20Heart%20Beats.mp3</string>
		</dict>
		<key>28161</key>
		<dict>
			<key>Track ID</key><integer>28161</integer>
			<key>Size</key><integer>10813176</integer>
			<key>Total Time</key><integer>269871</integer>
			<key>Track Number</key><integer>1</integer>
			<key>Year</key><integer>1985</integer>
			<key>Date Modified</key><date>2013-10-19T04:21:07Z</date>
			<key>Date Added</key><date>2018-04-09T14:48:31Z</date>
			<key>Bit Rate</key><integer>320</integer>
			<key>Sample Rate</key><integer>44100</integer>
			<key>Play Count</key><integer>1</integer>
			<key>Play Date</key><integer>3642618329</integer>
			<key>Play Date UTC</key><date>2019-06-06T02:25:29Z</date>
			<key>Artwork Count</key><integer>1</integer>
			<key>Persistent ID</key><string>FE3E46B2BA76E677</string>
			<key>Track Type</key><string>File</string>
			<key>File Folder Count</key><integer>5</integer>
			<key>Library Folder Count</key><integer>1</integer>
			<key>Name</key><string>Dans Votre Monde</string>
			<key>Artist</key><string>End Of Data</string>
			<key>Album</key><string>Dans Votre Monde</string>
			<key>Genre</key><string>Coldwave</string>
			<key>Kind</key><string>MPEG audio file</string>
			<key>Comments</key><string>www.systemsofromance.com</string>
			<key>Location</key><string>file:///Users/tonyfischetti/Music/iTunes/iTunes%20Media/Music/End%20Of%20Data/Dans%20Votre%20Monde/01%20Dans%20Votre%20Monde.mp3</string>
		</dict>
		<key>28169</key>
		<dict>
			<key>Track ID</key><integer>28169</integer>
			<key>Size</key><integer>10428650</integer>
			<key>Total Time</key><integer>260257</integer>
			<key>Track Number</key><integer>2</integer>
			<key>Year</key><integer>1985</integer>
			<key>Date Modified</key><date>2013-10-19T04:21:07Z</date>
			<key>Date Added</key><date>2018-04-09T14:48:31Z</date>
			<key>Bit Rate</key><integer>320</integer>
			<key>Sample Rate</key><integer>44100</integer>
			<key>Play Count</key><integer>1</integer>
			<key>Play Date</key><integer>3642618589</integer>
			<key>Play Date UTC</key><date>2019-06-06T02:29:49Z</date>
			<key>Artwork Count</key><integer>1</integer>
			<key>Persistent ID</key><string>C6CB2F7EC29EAC1F</string>
			<key>Track Type</key><string>File</string>
			<key>File Folder Count</key><integer>5</integer>
			<key>Library Folder Count</key><integer>1</integer>
			<key>Name</key><string>Movies Drama</string>
			<key>Artist</key><string>End Of Data</string>
			<key>Album</key><string>Dans Votre Monde</string>
			<key>Genre</key><string>Coldwave</string>
			<key>Kind</key><string>MPEG audio file</string>
			<key>Comments</key><string>www.systemsofromance.com</string>
			<key>Location</key><string>file:///Users/tonyfischetti/Music/iTunes/iTunes%20Media/Music/End%20Of%20Data/Dans%20Votre%20Monde/02%20Movies%20Drama.mp3</string>
		</dict>
		<key>28155</key>
		<dict>
			<key>Track ID</key><integer>28155</integer>
			<key>Size</key><integer>15288470</integer>
			<key>Total Time</key><integer>381753</integer>
			<key>Track Number</key><integer>3</integer>
			<key>Year</key><integer>1985</integer>
			<key>Date Modified</key><date>2013-10-19T04:21:08Z</date>
			<key>Date Added</key><date>2018-04-09T14:48:31Z</date>
			<key>Bit Rate</key><integer>320</integer>
			<key>Sample Rate</key><integer>44100</integer>
			<key>Artwork Count</key><integer>1</integer>
			<key>Persistent ID</key><string>5A4F72AA434AF8BA</string>
			<key>Track Type</key><string>File</string>
			<key>File Folder Count</key><integer>5</integer>
			<key>Library Folder Count</key><integer>1</integer>
			<key>Name</key><string>Quetzalcoatl</string>
			<key>Artist</key><string>End Of Data</string>
			<key>Album</key><string>Dans Votre Monde</string>
			<key>Genre</key><string>Coldwave</string>
			<key>Kind</key><string>MPEG audio file</string>
			<key>Comments</key><string>www.systemsofromance.com</string>
			<key>Location</key><string>file:///Users/tonyfischetti/Music/iTunes/iTunes%20Media/Music/End%20Of%20Data/Dans%20Votre%20Monde/03%20Quetzalcoatl.mp3</string>
		</dict>
		<key>28157</key>
		<dict>
			<key>Track ID</key><integer>28157</integer>
			<key>Size</key><integer>6684777</integer>
			<key>Total Time</key><integer>166661</integer>
			<key>Track Number</key><integer>4</integer>
			<key>Year</key><integer>1985</integer>
			<key>Date Modified</key><date>2013-10-19T04:21:08Z</date>
			<key>Date Added</key><date>2018-04-09T14:48:31Z</date>
			<key>Bit Rate</key><integer>320</integer>
			<key>Sample Rate</key><integer>44100</integer>
			<key>Artwork Count</key><integer>1</integer>
			<key>Persistent ID</key><string>62C3AD4F8FFA7044</string>
			<key>Track Type</key><string>File</string>
			<key>File Folder Count</key><integer>5</integer>
			<key>Library Folder Count</key><integer>1</integer>
			<key>Name</key><string>Symphonie</string>
			<key>Artist</key><string>End Of Data</string>
			<key>Album</key><string>Dans Votre Monde</string>
			<key>Genre</key><string>Coldwave</string>
			<key>Kind</key><string>MPEG audio file</string>
			<key>Comments</key><string>www.systemsofromance.com</string>
			<key>Location</key><string>file:///Users/tonyfischetti/Music/iTunes/iTunes%20Media/Music/End%20Of%20Data/Dans%20Votre%20Monde/04%20Symphonie.mp3</string>
		</dict>
		<key>28163</key>
		<dict>
			<key>Track ID</key><integer>28163</integer>
			<key>Size</key><integer>11860165</integer>
			<key>Total Time</key><integer>296045</integer>
			<key>Track Number</key><integer>5</integer>
			<key>Year</key><integer>1985</integer>
			<key>Date Modified</key><date>2013-10-19T04:21:09Z</date>
			<key>Date Added</key><date>2018-04-09T14:48:31Z</date>
			<key>Bit Rate</key><integer>320</integer>
			<key>Sample Rate</key><integer>44100</integer>
			<key>Artwork Count</key><integer>1</integer>
			<key>Persistent ID</key><string>7DD38406F38F41EC</string>
			<key>Track Type</key><string>File</string>
			<key>File Folder Count</key><integer>5</integer>
			<key>Library Folder Count</key><integer>1</integer>
			<key>Name</key><string>La Rive Asiatique</string>
			<key>Artist</key><string>End Of Data</string>
			<key>Album</key><string>Dans Votre Monde</string>
			<key>Genre</key><string>Coldwave</string>
			<key>Kind</key><string>MPEG audio file</string>
			<key>Comments</key><string>www.systemsofromance.com</string>
			<key>Location</key><string>file:///Users/tonyfischetti/Music/iTunes/iTunes%20Media/Music/End%20Of%20Data/Dans%20Votre%20Monde/05%20La%20Rive%20Asiatique.mp3</string>
		</dict>
		<key>28165</key>
		<dict>
			<key>Track ID</key><integer>28165</integer>
			<key>Size</key><integer>8273037</integer>
			<key>Total Time</key><integer>206367</integer>
			<key>Track Number</key><integer>6</integer>
			<key>Year</key><integer>1985</integer>
			<key>Date Modified</key><date>2013-10-19T04:21:09Z</date>
			<key>Date Added</key><date>2018-04-09T14:48:31Z</date>
			<key>Bit Rate</key><integer>320</integer>
			<key>Sample Rate</key><integer>44100</integer>
			<key>Artwork Count</key><integer>1</integer>
			<key>Persistent ID</key><string>15433E7BF19C4DD5</string>
			<key>Track Type</key><string>File</string>
			<key>File Folder Count</key><integer>5</integer>
			<key>Library Folder Count</key><integer>1</integer>
			<key>Name</key><string>Atttrra (Vers Le Miroir)</string>
			<key>Artist</key><string>End Of Data</string>
			<key>Album</key><string>Dans Votre Monde</string>
			<key>Genre</key><string>Coldwave</string>
			<key>Kind</key><string>MPEG audio file</string>
			<key>Comments</key><string>www.systemsofromance.com</string>
			<key>Location</key><string>file:///Users/tonyfischetti/Music/iTunes/iTunes%20Media/Music/End%20Of%20Data/Dans%20Votre%20Monde/06%20Atttrra%20(Vers%20Le%20Miroir).mp3</string>
		</dict>
		<key>28159</key>
		<dict>
			<key>Track ID</key><integer>28159</integer>
			<key>Size</key><integer>9616758</integer>
			<key>Total Time</key><integer>239960</integer>
			<key>Track Number</key><integer>7</integer>
			<key>Year</key><integer>1985</integer>
			<key>Date Modified</key><date>2013-10-19T04:21:09Z</date>
			<key>Date Added</key><date>2018-04-09T14:48:31Z</date>
			<key>Bit Rate</key><integer>320</integer>
			<key>Sample Rate</key><integer>44100</integer>
			<key>Play Count</key><integer>1</integer>
			<key>Play Date</key><integer>3642774739</integer>
			<key>Play Date UTC</key><date>2019-06-07T21:52:19Z</date>
			<key>Artwork Count</key><integer>1</integer>
			<key>Persistent ID</key><string>2E7EF9661CAF06ED</string>
			<key>Track Type</key><string>File</string>
			<key>File Folder Count</key><integer>5</integer>
			<key>Library Folder Count</key><integer>1</integer>
			<key>Name</key><string>Venice</string>
			<key>Artist</key><string>End Of Data</string>
			<key>Album</key><string>Dans Votre Monde</string>
			<key>Genre</key><string>Coldwave</string>
			<key>Kind</key><string>MPEG audio file</string>
			<key>Comments</key><string>www.systemsofromance.com</string>
			<key>Location</key><string>file:///Users/tonyfischetti/Music/iTunes/iTunes%20Media/Music/End%20Of%20Data/Dans%20Votre%20Monde/07%20Venice.mp3</string>
		</dict>
		<key>28167</key>
		<dict>
			<key>Track ID</key><integer>28167</integer>
			<key>Size</key><integer>7101689</integer>
			<key>Total Time</key><integer>177084</integer>
			<key>Track Number</key><integer>8</integer>
			<key>Year</key><integer>1985</integer>
			<key>Date Modified</key><date>2013-10-19T04:21:10Z</date>
			<key>Date Added</key><date>2018-04-09T14:48:31Z</date>
			<key>Bit Rate</key><integer>320</integer>
			<key>Sample Rate</key><integer>44100</integer>
			<key>Artwork Count</key><integer>1</integer>
			<key>Persistent ID</key><string>40372C0D4611B5F2</string>
			<key>Track Type</key><string>File</string>
			<key>File Folder Count</key><integer>5</integer>
			<key>Library Folder Count</key><integer>1</integer>
			<key>Name</key><string>D.M.C.</string>
			<key>Artist</key><string>End Of Data</string>
			<key>Album</key><string>Dans Votre Monde</string>
			<key>Genre</key><string>Coldwave</string>
			<key>Kind</key><string>MPEG audio file</string>
			<key>Comments</key><string>www.systemsofromance.com</string>
			<key>Location</key><string>file:///Users/tonyfischetti/Music/iTunes/iTunes%20Media/Music/End%20Of%20Data/Dans%20Votre%20Monde/08%20D.M.C..mp3</string>
		</dict>
		<key>49255</key>
		<dict>
			<key>Track ID</key><integer>49255</integer>
			<key>Size</key><integer>17047468</integer>
			<key>Total Time</key><integer>425168</integer>
			<key>Track Number</key><integer>4</integer>
			<key>Year</key><integer>1984</integer>
			<key>Date Modified</key><date>2013-10-19T03:59:41Z</date>
			<key>Date Added</key><date>2018-04-09T14:48:31Z</date>
			<key>Bit Rate</key><integer>320</integer>
			<key>Sample Rate</key><integer>44100</integer>
			<key>Artwork Count</key><integer>1</integer>
			<key>Persistent ID</key><string>A70612DE4C50ED87</string>
			<key>Track Type</key><string>File</string>
			<key>File Folder Count</key><integer>5</integer>
			<key>Library Folder Count</key><integer>1</integer>
			<key>Name</key><string>Pale Jade Eyes</string>
			<key>Artist</key><string>A Love Sound</string>
			<key>Album</key><string>I Need 12''</string>
			<key>Genre</key><string>Coldwave</string>
			<key>Kind</key><string>MPEG audio file</string>
			<key>Comments</key><string>www.systemsofromance.com</string>
			<key>Sort Artist</key><string>Love Sound</string>
			<key>Location</key><string>file:///Users/tonyfischetti/Music/iTunes/iTunes%20Media/Music/A%20Love%20Sound/I%20Need%2012''/04%20Pale%20Jade%20Eyes.mp3</string>
		</dict>
		<key>35467</key>
		<dict>
			<key>Track ID</key><integer>35467</integer>
			<key>Size</key><integer>6133080</integer>
			<key>Total Time</key><integer>254615</integer>
			<key>Track Number</key><integer>1</integer>
			<key>Track Count</key><integer>15</integer>
			<key>Year</key><integer>1990</integer>
			<key>Date Modified</key><date>2013-10-26T02:52:08Z</date>
			<key>Date Added</key><date>2018-04-09T14:48:31Z</date>
			<key>Bit Rate</key><integer>192</integer>
			<key>Sample Rate</key><integer>44100</integer>
			<key>Compilation</key><true/>
			<key>Artwork Count</key><integer>1</integer>
			<key>Persistent ID</key><string>47F243A7B0E51BFD</string>
			<key>Track Type</key><string>File</string>
			<key>File Folder Count</key><integer>5</integer>
			<key>Library Folder Count</key><integer>1</integer>
			<key>Name</key><string>Futile Research</string>
			<key>Artist</key><string>No Words</string>
			<key>Album</key><string>Unreleased III</string>
			<key>Genre</key><string>Coldwave</string>
			<key>Kind</key><string>MPEG audio file</string>
			<key>Comments</key><string>www.systemsofromance.com</string>
			<key>Location</key><string>file:///Users/tonyfischetti/Music/iTunes/iTunes%20Media/Music/Compilations/Unreleased%20III/01%20Futile%20Research.mp3</string>
		</dict>
		<key>35475</key>
		<dict>
			<key>Track ID</key><integer>35475</integer>
			<key>Size</key><integer>2096875</integer>
			<key>Total Time</key><integer>86439</integer>
			<key>Track Number</key><integer>2</integer>
			<key>Track Count</key><integer>15</integer>
			<key>Year</key><integer>1990</integer>
			<key>Date Modified</key><date>2013-10-26T02:52:08Z</date>
			<key>Date Added</key><date>2018-04-09T14:48:31Z</date>
			<key>Bit Rate</key><integer>192</integer>
			<key>Sample Rate</key><integer>44100</integer>
			<key>Compilation</key><true/>
			<key>Artwork Count</key><integer>1</integer>
			<key>Persistent ID</key><string>E1A4FD37496BB681</string>
			<key>Track Type</key><string>File</string>
			<key>File Folder Count</key><integer>5</integer>
			<key>Library Folder Count</key><integer>1</integer>
			<key>Name</key><string>Hélioneiros No 1</string>
			<key>Artist</key><string>Vincent Legallo</string>
			<key>Album</key><string>Unreleased III</string>
			<key>Genre</key><string>Coldwave</string>
			<key>Kind</key><string>MPEG audio file</string>
			<key>Comments</key><string>www.systemsofromance.com</string>
			<key>Location</key><string>file:///Users/tonyfischetti/Music/iTunes/iTunes%20Media/Music/Compilations/Unreleased%20III/02%20He%CC%81lioneiros%20No%201.mp3</string>
		</dict>
		<key>35473</key>
		<dict>
			<key>Track ID</key><integer>35473</integer>
			<key>Size</key><integer>3281757</integer>
			<key>Total Time</key><integer>135810</integer>
			<key>Track Number</key><integer>3</integer>
			<key>Track Count</key><integer>15</integer>
			<key>Year</key><integer>1990</integer>
			<key>Date Modified</key><date>2013-10-26T02:52:08Z</date>
			<key>Date Added</key><date>2018-04-09T14:48:31Z</date>
			<key>Bit Rate</key><integer>192</integer>
			<key>Sample Rate</key><integer>44100</integer>
			<key>Compilation</key><true/>
			<key>Artwork Count</key><integer>1</integer>
			<key>Persistent ID</key><string>E4D5B6D1006F5F92</string>
			<key>Track Type</key><string>File</string>
			<key>File Folder Count</key><integer>5</integer>
			<key>Library Folder Count</key><integer>1</integer>
			<key>Name</key><string>Silent Call</string>
			<key>Artist</key><string>No Words</string>
			<key>Album</key><string>Unreleased III</string>
			<key>Genre</key><string>Coldwave</string>
			<key>Kind</key><string>MPEG audio file</string>
			<key>Comments</key><string>www.systemsofromance.com</string>
			<key>Location</key><string>file:///Users/tonyfischetti/Music/iTunes/iTunes%20Media/Music/Compilations/Unreleased%20III/03%20Silent%20Call.mp3</string>
		</dict>
		<key>35485</key>
		<dict>
			<key>Track ID</key><integer>35485</integer>
			<key>Size</key><integer>2976441</integer>
			<key>Total Time</key><integer>123088</integer>
			<key>Track Number</key><integer>4</integer>
			<key>Track Count</key><integer>15</integer>
			<key>Year</key><integer>1990</integer>
			<key>Date Modified</key><date>2013-10-26T02:52:08Z</date>
			<key>Date Added</key><date>2018-04-09T14:48:31Z</date>
			<key>Bit Rate</key><integer>192</integer>
			<key>Sample Rate</key><integer>44100</integer>
			<key>Compilation</key><true/>
			<key>Artwork Count</key><integer>1</integer>
			<key>Persistent ID</key><string>E4B58D674FDCA674</string>
			<key>Track Type</key><string>File</string>
			<key>File Folder Count</key><integer>5</integer>
			<key>Library Folder Count</key><integer>1</integer>
			<key>Name</key><string>Wet Button</string>
			<key>Artist</key><string>Asylum Party</string>
			<key>Album</key><string>Unreleased III</string>
			<key>Genre</key><string>Coldwave</string>
			<key>Kind</key><string>MPEG audio file</string>
			<key>Comments</key><string>www.systemsofromance.com</string>
			<key>Location</key><string>file:///Users/tonyfischetti/Music/iTunes/iTunes%20Media/Music/Compilations/Unreleased%20III/04%20Wet%20Button.mp3</string>
		</dict>
		<key>35489</key>
		<dict>
			<key>Track ID</key><integer>35489</integer>
			<key>Size</key><integer>3563899</integer>
			<key>Total Time</key><integer>147565</integer>
			<key>Track Number</key><integer>5</integer>
			<key>Track Count</key><integer>15</integer>
			<key>Year</key><integer>1990</integer>
			<key>Date Modified</key><date>2013-10-26T02:52:08Z</date>
			<key>Date Added</key><date>2018-04-09T14:48:31Z</date>
			<key>Bit Rate</key><integer>192</integer>
			<key>Sample Rate</key><integer>44100</integer>
			<key>Compilation</key><true/>
			<key>Artwork Count</key><integer>1</integer>
			<key>Persistent ID</key><string>694AD89D9E366795</string>
			<key>Track Type</key><string>File</string>
			<key>File Folder Count</key><integer>5</integer>
			<key>Library Folder Count</key><integer>1</integer>
			<key>Name</key><string>Unity Mitford</string>
			<key>Artist</key><string>Rise And Fall Of A Decade</string>
			<key>Album</key><string>Unreleased III</string>
			<key>Genre</key><string>Coldwave</string>
			<key>Kind</key><string>MPEG audio file</string>
			<key>Comments</key><string>www.systemsofromance.com</string>
			<key>Location</key><string>file:///Users/tonyfischetti/Music/iTunes/iTunes%20Media/Music/Compilations/Unreleased%20III/05%20Unity%20Mitford.mp3</string>
		</dict>
		<key>35479</key>
		<dict>
			<key>Track ID</key><integer>35479</integer>
			<key>Size</key><integer>4550054</integer>
			<key>Total Time</key><integer>188656</integer>
			<key>Track Number</key><integer>6</integer>
			<key>Track Count</key><integer>15</integer>
			<key>Year</key><integer>1990</integer>
			<key>Date Modified</key><date>2013-10-26T02:52:08Z</date>
			<key>Date Added</key><date>2018-04-09T14:48:31Z</date>
			<key>Bit Rate</key><integer>192</integer>
			<key>Sample Rate</key><integer>44100</integer>
			<key>Compilation</key><true/>
			<key>Artwork Count</key><integer>1</integer>
			<key>Persistent ID</key><string>DBC87913F5B4807D</string>
			<key>Track Type</key><string>File</string>
			<key>File Folder Count</key><integer>5</integer>
			<key>Library Folder Count</key><integer>1</integer>
			<key>Name</key><string>Fracture</string>
			<key>Artist</key><string>Trees Dance</string>
			<key>Album</key><string>Unreleased III</string>
			<key>Genre</key><string>Coldwave</string>
			<key>Kind</key><string>MPEG audio file</string>
			<key>Comments</key><string>www.systemsofromance.com</string>
			<key>Location</key><string>file:///Users/tonyfischetti/Music/iTunes/iTunes%20Media/Music/Compilations/Unreleased%20III/06%20Fracture.mp3</string>
		</dict>
		<key>35463</key>
		<dict>
			<key>Track ID</key><integer>35463</integer>
			<key>Size</key><integer>2739475</integer>
			<key>Total Time</key><integer>113214</integer>
			<key>Track Number</key><integer>7</integer>
			<key>Track Count</key><integer>15</integer>
			<key>Year</key><integer>1990</integer>
			<key>Date Modified</key><date>2013-10-26T02:52:08Z</date>
			<key>Date Added</key><date>2018-04-09T14:48:31Z</date>
			<key>Bit Rate</key><integer>192</integer>
			<key>Sample Rate</key><integer>44100</integer>
			<key>Compilation</key><true/>
			<key>Artwork Count</key><integer>1</integer>
			<key>Persistent ID</key><string>54F2C0223C781A5B</string>
			<key>Track Type</key><string>File</string>
			<key>File Folder Count</key><integer>5</integer>
			<key>Library Folder Count</key><integer>1</integer>
			<key>Name</key><string>Theme Kurland</string>
			<key>Artist</key><string>Rise And Fall Of A Decade</string>
			<key>Album</key><string>Unreleased III</string>
			<key>Genre</key><string>Coldwave</string>
			<key>Kind</key><string>MPEG audio file</string>
			<key>Comments</key><string>www.systemsofromance.com</string>
			<key>Location</key><string>file:///Users/tonyfischetti/Music/iTunes/iTunes%20Media/Music/Compilations/Unreleased%20III/07%20Theme%20Kurland.mp3</string>
		</dict>
		<key>35487</key>
		<dict>
			<key>Track ID</key><integer>35487</integer>
			<key>Size</key><integer>3160135</integer>
			<key>Total Time</key><integer>130742</integer>
			<key>Track Number</key><integer>8</integer>
			<key>Track Count</key><integer>15</integer>
			<key>Year</key><integer>1990</integer>
			<key>Date Modified</key><date>2013-10-26T02:52:08Z</date>
			<key>Date Added</key><date>2018-04-09T14:48:31Z</date>
			<key>Bit Rate</key><integer>192</integer>
			<key>Sample Rate</key><integer>44100</integer>
			<key>Compilation</key><true/>
			<key>Artwork Count</key><integer>1</integer>
			<key>Persistent ID</key><string>6EC3574414FBC877</string>
			<key>Track Type</key><string>File</string>
			<key>File Folder Count</key><integer>5</integer>
			<key>Library Folder Count</key><integer>1</integer>
			<key>Name</key><string>Classical Side</string>
			<key>Artist</key><string>No Words</string>
			<key>Album</key><string>Unreleased III</string>
			<key>Genre</key><string>Coldwave</string>
			<key>Kind</key><string>MPEG audio file</string>
			<key>Comments</key><string>www.systemsofromance.com</string>
			<key>Location</key><string>file:///Users/tonyfischetti/Music/iTunes/iTunes%20Media/Music/Compilations/Unreleased%20III/08%20Classical%20Side.mp3</string>
		</dict>
		<key>35491</key>
		<dict>
			<key>Track ID</key><integer>35491</integer>
			<key>Size</key><integer>6407050</integer>
			<key>Total Time</key><integer>266031</integer>
			<key>Track Number</key><integer>9</integer>
			<key>Track Count</key><integer>15</integer>
			<key>Year</key><integer>1990</integer>
			<key>Date Modified</key><date>2013-10-26T02:52:08Z</date>
			<key>Date Added</key><date>2018-04-09T14:48:31Z</date>
			<key>Bit Rate</key><integer>192</integer>
			<key>Sample Rate</key><integer>44100</integer>
			<key>Compilation</key><true/>
			<key>Artwork Count</key><integer>1</integer>
			<key>Persistent ID</key><string>CB074DC15EC2B010</string>
			<key>Track Type</key><string>File</string>
			<key>File Folder Count</key><integer>5</integer>
			<key>Library Folder Count</key><integer>1</integer>
			<key>Name</key><string>Seraphic</string>
			<key>Artist</key><string>In The Nursery</string>
			<key>Album</key><string>Unreleased III</string>
			<key>Genre</key><string>Coldwave</string>
			<key>Kind</key><string>MPEG audio file</string>
			<key>Comments</key><string>www.systemsofromance.com</string>
			<key>Location</key><string>file:///Users/tonyfischetti/Music/iTunes/iTunes%20Media/Music/Compilations/Unreleased%20III/09%20Seraphic.mp3</string>
		</dict>
		<key>35481</key>
		<dict>
			<key>Track ID</key><integer>35481</integer>
			<key>Size</key><integer>3556366</integer>
			<key>Total Time</key><integer>147252</integer>
			<key>Track Number</key><integer>10</integer>
			<key>Track Count</key><integer>15</integer>
			<key>Year</key><integer>1990</integer>
			<key>Date Modified</key><date>2013-10-26T02:52:08Z</date>
			<key>Date Added</key><date>2018-04-09T14:48:31Z</date>
			<key>Bit Rate</key><integer>192</integer>
			<key>Sample Rate</key><integer>44100</integer>
			<key>Compilation</key><true/>
			<key>Artwork Count</key><integer>1</integer>
			<key>Persistent ID</key><string>E8D860907753688E</string>
			<key>Track Type</key><string>File</string>
			<key>File Folder Count</key><integer>5</integer>
			<key>Library Folder Count</key><integer>1</integer>
			<key>Name</key><string>Lust In Holy Dust</string>
			<key>Artist</key><string>Trees Dance</string>
			<key>Album</key><string>Unreleased III</string>
			<key>Genre</key><string>Coldwave</string>
			<key>Kind</key><string>MPEG audio file</string>
			<key>Comments</key><string>www.systemsofromance.com</string>
			<key>Location</key><string>file:///Users/tonyfischetti/Music/iTunes/iTunes%20Media/Music/Compilations/Unreleased%20III/10%20Lust%20In%20Holy%20Dust.mp3</string>
		</dict>
		<key>35483</key>
		<dict>
			<key>Track ID</key><integer>35483</integer>
			<key>Size</key><integer>5921228</integer>
			<key>Total Time</key><integer>245786</integer>
			<key>Track Number</key><integer>11</integer>
			<key>Track Count</key><integer>15</integer>
			<key>Year</key><integer>1990</integer>
			<key>Date Modified</key><date>2013-10-26T02:52:08Z</date>
			<key>Date Added</key><date>2018-04-09T14:48:31Z</date>
			<key>Bit Rate</key><integer>192</integer>
			<key>Sample Rate</key><integer>44100</integer>
			<key>Compilation</key><true/>
			<key>Artwork Count</key><integer>1</integer>
			<key>Persistent ID</key><string>DFFEA64D9550ED43</string>
			<key>Track Type</key><string>File</string>
			<key>File Folder Count</key><integer>5</integer>
			<key>Library Folder Count</key><integer>1</integer>
			<key>Name</key><string>Galdhöpiggen Glittertind</string>
			<key>Artist</key><string>Rise And Fall Of A Decade</string>
			<key>Album</key><string>Unreleased III</string>
			<key>Genre</key><string>Coldwave</string>
			<key>Kind</key><string>MPEG audio file</string>
			<key>Comments</key><string>www.systemsofromance.com</string>
			<key>Location</key><string>file:///Users/tonyfischetti/Music/iTunes/iTunes%20Media/Music/Compilations/Unreleased%20III/11%20Galdho%CC%88piggen%20Glittertind.mp3</string>
		</dict>
		<key>35471</key>
		<dict>
			<key>Track ID</key><integer>35471</integer>
			<key>Size</key><integer>3232232</integer>
			<key>Total Time</key><integer>133746</integer>
			<key>Track Number</key><integer>12</integer>
			<key>Track Count</key><integer>15</integer>
			<key>Year</key><integer>1990</integer>
			<key>Date Modified</key><date>2013-10-26T02:52:08Z</date>
			<key>Date Added</key><date>2018-04-09T14:48:31Z</date>
			<key>Bit Rate</key><integer>192</integer>
			<key>Sample Rate</key><integer>44100</integer>
			<key>Compilation</key><true/>
			<key>Artwork Count</key><integer>1</integer>
			<key>Persistent ID</key><string>4725CEB26AE59606</string>
			<key>Track Type</key><string>File</string>
			<key>File Folder Count</key><integer>5</integer>
			<key>Library Folder Count</key><integer>1</integer>
			<key>Name</key><string>No Access</string>
			<key>Artist</key><string>Trees Dance</string>
			<key>Album</key><string>Unreleased III</string>
			<key>Genre</key><string>Coldwave</string>
			<key>Kind</key><string>MPEG audio file</string>
			<key>Comments</key><string>www.systemsofromance.com</string>
			<key>Location</key><string>file:///Users/tonyfischetti/Music/iTunes/iTunes%20Media/Music/Compilations/Unreleased%20III/12%20No%20Access.mp3</string>
		</dict>
		<key>35477</key>
		<dict>
			<key>Track ID</key><integer>35477</integer>
			<key>Size</key><integer>4840967</integer>
			<key>Total Time</key><integer>200777</integer>
			<key>Track Number</key><integer>13</integer>
			<key>Track Count</key><integer>15</integer>
			<key>Year</key><integer>1990</integer>
			<key>Date Modified</key><date>2013-10-26T02:52:08Z</date>
			<key>Date Added</key><date>2018-04-09T14:48:31Z</date>
			<key>Bit Rate</key><integer>192</integer>
			<key>Sample Rate</key><integer>44100</integer>
			<key>Compilation</key><true/>
			<key>Artwork Count</key><integer>1</integer>
			<key>Persistent ID</key><string>64DEBFEEE961656A</string>
			<key>Track Type</key><string>File</string>
			<key>File Folder Count</key><integer>5</integer>
			<key>Library Folder Count</key><integer>1</integer>
			<key>Name</key><string>Orges Allemands</string>
			<key>Artist</key><string>Vincent Legallo</string>
			<key>Album</key><string>Unreleased III</string>
			<key>Genre</key><string>Coldwave</string>
			<key>Kind</key><string>MPEG audio file</string>
			<key>Comments</key><string>www.systemsofromance.com</string>
			<key>Location</key><string>file:///Users/tonyfischetti/Music/iTunes/iTunes%20Media/Music/Compilations/Unreleased%20III/13%20Orges%20Allemands.mp3</string>
		</dict>
		<key>35465</key>
		<dict>
			<key>Track ID</key><integer>35465</integer>
			<key>Size</key><integer>3384592</integer>
			<key>Total Time</key><integer>140094</integer>
			<key>Track Number</key><integer>14</integer>
			<key>Track Count</key><integer>15</integer>
			<key>Year</key><integer>1990</integer>
			<key>Date Modified</key><date>2013-10-26T02:52:08Z</date>
			<key>Date Added</key><date>2018-04-09T14:48:31Z</date>
			<key>Bit Rate</key><integer>192</integer>
			<key>Sample Rate</key><integer>44100</integer>
			<key>Compilation</key><true/>
			<key>Artwork Count</key><integer>1</integer>
			<key>Persistent ID</key><string>D5B5D0FCB4E234A6</string>
			<key>Track Type</key><string>File</string>
			<key>File Folder Count</key><integer>5</integer>
			<key>Library Folder Count</key><integer>1</integer>
			<key>Name</key><string>Prémonition</string>
			<key>Artist</key><string>No Words</string>
			<key>Album</key><string>Unreleased III</string>
			<key>Genre</key><string>Coldwave</string>
			<key>Kind</key><string>MPEG audio file</string>
			<key>Comments</key><string>www.systemsofromance.com</string>
			<key>Location</key><string>file:///Users/tonyfischetti/Music/iTunes/iTunes%20Media/Music/Compilations/Unreleased%20III/14%20Pre%CC%81monition.mp3</string>
		</dict>
		<key>35469</key>
		<dict>
			<key>Track ID</key><integer>35469</integer>
			<key>Size</key><integer>4630347</integer>
			<key>Total Time</key><integer>192000</integer>
			<key>Track Number</key><integer>15</integer>
			<key>Track Count</key><integer>15</integer>
			<key>Year</key><integer>1990</integer>
			<key>Date Modified</key><date>2013-10-26T02:52:08Z</date>
			<key>Date Added</key><date>2018-04-09T14:48:31Z</date>
			<key>Bit Rate</key><integer>192</integer>
			<key>Sample Rate</key><integer>44100</integer>
			<key>Compilation</key><true/>
			<key>Artwork Count</key><integer>1</integer>
			<key>Persistent ID</key><string>9A00FE4A19FADFB9</string>
			<key>Track Type</key><string>File</string>
			<key>File Folder Count</key><integer>5</integer>
			<key>Library Folder Count</key><integer>1</integer>
			<key>Name</key><string>Hommage À Gaétan Blondeau</string>
			<key>Artist</key><string>No Words</string>
			<key>Album</key><string>Unreleased III</string>
			<key>Genre</key><string>Coldwave</string>
			<key>Kind</key><string>MPEG audio file</string>
			<key>Comments</key><string>www.systemsofromance.com</string>
			<key>Location</key><string>file:///Users/tonyfischetti/Music/iTunes/iTunes%20Media/Music/Compilations/Unreleased%20III/15%20Hommage%20A%CC%80%20Gae%CC%81tan%20Blondeau.mp3</string>
		</dict>
		<key>34985</key>
		<dict>
			<key>Track ID</key><integer>34985</integer>
			<key>Size</key><integer>10462132</integer>
			<key>Total Time</key><integer>260832</integer>
			<key>Track Number</key><integer>1</integer>
			<key>Date Modified</key><date>2013-10-19T04:38:56Z</date>
			<key>Date Added</key><date>2018-04-09T14:48:31Z</date>
			<key>Bit Rate</key><integer>320</integer>
			<key>Sample Rate</key><integer>44100</integer>
			<key>Play Count</key><integer>1</integer>
			<key>Play Date</key><integer>3614021319</integer>
			<key>Play Date UTC</key><date>2018-07-10T02:48:39Z</date>
			<key>Release Date</key><date>2008-02-02T08:00:00Z</date>
			<key>Artwork Count</key><integer>1</integer>
			<key>Persistent ID</key><string>C93C734EFF195DFC</string>
			<key>Track Type</key><string>File</string>
			<key>File Folder Count</key><integer>5</integer>
			<key>Library Folder Count</key><integer>1</integer>
			<key>Name</key><string>Tarantula Scream</string>
			<key>Artist</key><string>Iron Curtain</string>
			<key>Album</key><string>Desertion</string>
			<key>Genre</key><string>Darkwave</string>
			<key>Kind</key><string>MPEG audio file</string>
			<key>Location</key><string>file:///Users/tonyfischetti/Music/iTunes/iTunes%20Media/Music/Iron%20Curtain/Desertion/01%20Tarantula%20Scream.mp3</string>
		</dict>
		<key>34975</key>
		<dict>
			<key>Track ID</key><integer>34975</integer>
			<key>Size</key><integer>15955159</integer>
			<key>Total Time</key><integer>398158</integer>
			<key>Track Number</key><integer>2</integer>
			<key>Date Modified</key><date>2013-10-19T04:38:57Z</date>
			<key>Date Added</key><date>2018-04-09T14:48:31Z</date>
			<key>Bit Rate</key><integer>320</integer>
			<key>Sample Rate</key><integer>44100</integer>
			<key>Play Count</key><integer>1</integer>
			<key>Play Date</key><integer>3614021723</integer>
			<key>Play Date UTC</key><date>2018-07-10T02:55:23Z</date>
			<key>Release Date</key><date>2008-02-02T08:00:00Z</date>
			<key>Artwork Count</key><integer>1</integer>
			<key>Persistent ID</key><string>3E5BBAA630C4C668</string>
			<key>Track Type</key><string>File</string>
			<key>File Folder Count</key><integer>5</integer>
			<key>Library Folder Count</key><integer>1</integer>
			<key>Name</key><string>First Punk Wars</string>
			<key>Artist</key><string>Iron Curtain</string>
			<key>Album</key><string>Desertion</string>
			<key>Genre</key><string>Darkwave</string>
			<key>Kind</key><string>MPEG audio file</string>
			<key>Location</key><string>file:///Users/tonyfischetti/Music/iTunes/iTunes%20Media/Music/Iron%20Curtain/Desertion/02%20First%20Punk%20Wars.mp3</string>
		</dict>
		<key>34977</key>
		<dict>
			<key>Track ID</key><integer>34977</integer>
			<key>Size</key><integer>11454779</integer>
			<key>Total Time</key><integer>285648</integer>
			<key>Track Number</key><integer>3</integer>
			<key>Date Modified</key><date>2013-10-19T04:38:57Z</date>
			<key>Date Added</key><date>2018-04-09T14:48:31Z</date>
			<key>Bit Rate</key><integer>320</integer>
			<key>Sample Rate</key><integer>44100</integer>
			<key>Play Count</key><integer>1</integer>
			<key>Play Date</key><integer>3614022008</integer>
			<key>Play Date UTC</key><date>2018-07-10T03:00:08Z</date>
			<key>Release Date</key><date>2008-02-02T08:00:00Z</date>
			<key>Artwork Count</key><integer>1</integer>
			<key>Persistent ID</key><string>38189051D6DDB2E0</string>
			<key>Track Type</key><string>File</string>
			<key>File Folder Count</key><integer>5</integer>
			<key>Library Folder Count</key><integer>1</integer>
			<key>Name</key><string>The Condos</string>
			<key>Artist</key><string>Iron Curtain</string>
			<key>Album</key><string>Desertion</string>
			<key>Genre</key><string>Darkwave</string>
			<key>Kind</key><string>MPEG audio file</string>
			<key>Sort Name</key><string>Condos</string>
			<key>Location</key><string>file:///Users/tonyfischetti/Music/iTunes/iTunes%20Media/Music/Iron%20Curtain/Desertion/03%20The%20Condos.mp3</string>
		</dict>
		<key>34993</key>
		<dict>
			<key>Track ID</key><integer>34993</integer>
			<key>Size</key><integer>12573872</integer>
			<key>Total Time</key><integer>313626</integer>
			<key>Track Number</key><integer>4</integer>
			<key>Date Modified</key><date>2013-10-19T04:38:58Z</date>
			<key>Date Added</key><date>2018-04-09T14:48:31Z</date>
			<key>Bit Rate</key><integer>320</integer>
			<key>Sample Rate</key><integer>44100</integer>
			<key>Play Count</key><integer>1</integer>
			<key>Play Date</key><integer>3614022322</integer>
			<key>Play Date UTC</key><date>2018-07-10T03:05:22Z</date>
			<key>Release Date</key><date>2008-02-02T08:00:00Z</date>
			<key>Artwork Count</key><integer>1</integer>
			<key>Persistent ID</key><string>4417DA7964A73B5E</string>
			<key>Track Type</key><string>File</string>
			<key>File Folder Count</key><integer>5</integer>
			<key>Library Folder Count</key><integer>1</integer>
			<key>Name</key><string>Love Can Never Die</string>
			<key>Artist</key><string>Iron Curtain</string>
			<key>Album</key><string>Desertion</string>
			<key>Genre</key><string>Darkwave</string>
			<key>Kind</key><string>MPEG audio file</string>
			<key>Location</key><string>file:///Users/tonyfischetti/Music/iTunes/iTunes%20Media/Music/Iron%20Curtain/Desertion/04%20Love%20Can%20Never%20Die.mp3</string>
		</dict>
		<key>34983</key>
		<dict>
			<key>Track ID</key><integer>34983</integer>
			<key>Size</key><integer>13672048</integer>
			<key>Total Time</key><integer>341080</integer>
			<key>Track Number</key><integer>5</integer>
			<key>Date Modified</key><date>2013-10-19T04:38:58Z</date>
			<key>Date Added</key><date>2018-04-09T14:48:31Z</date>
			<key>Bit Rate</key><integer>320</integer>
			<key>Sample Rate</key><integer>44100</integer>
			<key>Release Date</key><date>2008-02-02T08:00:00Z</date>
			<key>Artwork Count</key><integer>1</integer>
			<key>Persistent ID</key><string>10558BA85CD6224E</string>
			<key>Track Type</key><string>File</string>
			<key>File Folder Count</key><integer>5</integer>
			<key>Library Folder Count</key><integer>1</integer>
			<key>Name</key><string>Shadow</string>
			<key>Artist</key><string>Iron Curtain</string>
			<key>Album</key><string>Desertion</string>
			<key>Genre</key><string>Darkwave</string>
			<key>Kind</key><string>MPEG audio file</string>
			<key>Location</key><string>file:///Users/tonyfischetti/Music/iTunes/iTunes%20Media/Music/Iron%20Curtain/Desertion/05%20Shadow.mp3</string>
		</dict>
		<key>34981</key>
		<dict>
			<key>Track ID</key><integer>34981</integer>
			<key>Size</key><integer>12114110</integer>
			<key>Total Time</key><integer>302132</integer>
			<key>Track Number</key><integer>6</integer>
			<key>Date Modified</key><date>2013-10-19T04:38:59Z</date>
			<key>Date Added</key><date>2018-04-09T14:48:31Z</date>
			<key>Bit Rate</key><integer>320</integer>
			<key>Sample Rate</key><integer>44100</integer>
			<key>Release Date</key><date>2008-02-02T08:00:00Z</date>
			<key>Artwork Count</key><integer>1</integer>
			<key>Persistent ID</key><string>F96D1B56296F0843</string>
			<key>Track Type</key><string>File</string>
			<key>File Folder Count</key><integer>5</integer>
			<key>Library Folder Count</key><integer>1</integer>
			<key>Name</key><string>The Burning</string>
			<key>Artist</key><string>Iron Curtain</string>
			<key>Album</key><string>Desertion</string>
			<key>Genre</key><string>Darkwave</string>
			<key>Kind</key><string>MPEG audio file</string>
			<key>Sort Name</key><string>Burning</string>
			<key>Location</key><string>file:///Users/tonyfischetti/Music/iTunes/iTunes%20Media/Music/Iron%20Curtain/Desertion/06%20The%20Burning.mp3</string>
		</dict>
		<key>34979</key>
		<dict>
			<key>Track ID</key><integer>34979</integer>
			<key>Size</key><integer>8281426</integer>
			<key>Total Time</key><integer>206315</integer>
			<key>Track Number</key><integer>7</integer>
			<key>Date Modified</key><date>2013-10-19T04:38:59Z</date>
			<key>Date Added</key><date>2018-04-09T14:48:31Z</date>
			<key>Bit Rate</key><integer>320</integer>
			<key>Sample Rate</key><integer>44100</integer>
			<key>Release Date</key><date>2008-02-02T08:00:00Z</date>
			<key>Artwork Count</key><integer>1</integer>
			<key>Persistent ID</key><string>EB1DFCA648B411CC</string>
			<key>Track Type</key><string>File</string>
			<key>File Folder Count</key><integer>5</integer>
			<key>Library Folder Count</key><integer>1</integer>
			<key>Name</key><string>Terror Story</string>
			<key>Artist</key><string>Iron Curtain</string>
			<key>Album</key><string>Desertion</string>
			<key>Genre</key><string>Darkwave</string>
			<key>Kind</key><string>MPEG audio file</string>
			<key>Location</key><string>file:///Users/tonyfischetti/Music/iTunes/iTunes%20Media/Music/Iron%20Curtain/Desertion/07%20Terror%20Story.mp3</string>
		</dict>
		<key>34987</key>
		<dict>
			<key>Track ID</key><integer>34987</integer>
			<key>Size</key><integer>13088997</integer>
			<key>Total Time</key><integer>326504</integer>
			<key>Track Number</key><integer>8</integer>
			<key>Date Modified</key><date>2013-10-19T04:39:00Z</date>
			<key>Date Added</key><date>2018-04-09T14:48:31Z</date>
			<key>Bit Rate</key><integer>320</integer>
			<key>Sample Rate</key><integer>44100</integer>
			<key>Release Date</key><date>2008-02-02T08:00:00Z</date>
			<key>Artwork Count</key><integer>1</integer>
			<key>Persistent ID</key><string>6BDCBAF6BD062678</string>
			<key>Track Type</key><string>File</string>
			<key>File Folder Count</key><integer>5</integer>
			<key>Library Folder Count</key><integer>1</integer>
			<key>Name</key><string>Anorexia</string>
			<key>Artist</key><string>Iron Curtain</string>
			<key>Album</key><string>Desertion</string>
			<key>Genre</key><string>Darkwave</string>
			<key>Kind</key><string>MPEG audio file</string>
			<key>Location</key><string>file:///Users/tonyfischetti/Music/iTunes/iTunes%20Media/Music/Iron%20Curtain/Desertion/08%20Anorexia.mp3</string>
		</dict>
		<key>34997</key>
		<dict>
			<key>Track ID</key><integer>34997</integer>
			<key>Size</key><integer>10754700</integer>
			<key>Total Time</key><integer>268146</integer>
			<key>Track Number</key><integer>9</integer>
			<key>Date Modified</key><date>2013-10-19T04:39:00Z</date>
			<key>Date Added</key><date>2018-04-09T14:48:31Z</date>
			<key>Bit Rate</key><integer>320</integer>
			<key>Sample Rate</key><integer>44100</integer>
			<key>Release Date</key><date>2008-02-02T08:00:00Z</date>
			<key>Artwork Count</key><integer>1</integer>
			<key>Persistent ID</key><string>98282A8C5547C55F</string>
			<key>Track Type</key><string>File</string>
			<key>File Folder Count</key><integer>5</integer>
			<key>Library Folder Count</key><integer>1</integer>
			<key>Name</key><string>Like a Family</string>
			<key>Artist</key><string>Iron Curtain</string>
			<key>Album</key><string>Desertion</string>
			<key>Genre</key><string>Darkwave</string>
			<key>Kind</key><string>MPEG audio file</string>
			<key>Location</key><string>file:///Users/tonyfischetti/Music/iTunes/iTunes%20Media/Music/Iron%20Curtain/Desertion/09%20Like%20a%20Family.mp3</string>
		</dict>
		<key>34991</key>
		<dict>
			<key>Track ID</key><integer>34991</integer>
			<key>Size</key><integer>10279269</integer>
			<key>Total Time</key><integer>256261</integer>
			<key>Track Number</key><integer>10</integer>
			<key>Date Modified</key><date>2013-10-19T04:39:00Z</date>
			<key>Date Added</key><date>2018-04-09T14:48:31Z</date>
			<key>Bit Rate</key><integer>320</integer>
			<key>Sample Rate</key><integer>44100</integer>
			<key>Release Date</key><date>2008-02-02T08:00:00Z</date>
			<key>Artwork Count</key><integer>1</integer>
			<key>Persistent ID</key><string>B98EFADDB6CF63E2</string>
			<key>Track Type</key><string>File</string>
			<key>File Folder Count</key><integer>5</integer>
			<key>Library Folder Count</key><integer>1</integer>
			<key>Name</key><string>Telephone</string>
			<key>Artist</key><string>Iron Curtain</string>
			<key>Album</key><string>Desertion</string>
			<key>Genre</key><string>Darkwave</string>
			<key>Kind</key><string>MPEG audio file</string>
			<key>Location</key><string>file:///Users/tonyfischetti/Music/iTunes/iTunes%20Media/Music/Iron%20Curtain/Desertion/10%20Telephone.mp3</string>
		</dict>
		<key>34989</key>
		<dict>
			<key>Track ID</key><integer>34989</integer>
			<key>Size</key><integer>12317870</integer>
			<key>Total Time</key><integer>307226</integer>
			<key>Track Number</key><integer>11</integer>
			<key>Date Modified</key><date>2013-10-19T04:39:01Z</date>
			<key>Date Added</key><date>2018-04-09T14:48:31Z</date>
			<key>Bit Rate</key><integer>320</integer>
			<key>Sample Rate</key><integer>44100</integer>
			<key>Release Date</key><date>2008-02-02T08:00:00Z</date>
			<key>Artwork Count</key><integer>1</integer>
			<key>Persistent ID</key><string>7EC6EED80520589B</string>
			<key>Track Type</key><string>File</string>
			<key>File Folder Count</key><integer>5</integer>
			<key>Library Folder Count</key><integer>1</integer>
			<key>Name</key><string>Legalize Heroin</string>
			<key>Artist</key><string>Iron Curtain</string>
			<key>Album</key><string>Desertion</string>
			<key>Genre</key><string>Darkwave</string>
			<key>Kind</key><string>MPEG audio file</string>
			<key>Location</key><string>file:///Users/tonyfischetti/Music/iTunes/iTunes%20Media/Music/Iron%20Curtain/Desertion/11%20Legalize%20Heroin.mp3</string>
		</dict>
		<key>34995</key>
		<dict>
			<key>Track ID</key><integer>34995</integer>
			<key>Size</key><integer>11749448</integer>
			<key>Total Time</key><integer>293015</integer>
			<key>Track Number</key><integer>12</integer>
			<key>Date Modified</key><date>2013-10-19T04:39:01Z</date>
			<key>Date Added</key><date>2018-04-09T14:48:31Z</date>
			<key>Bit Rate</key><integer>320</integer>
			<key>Sample Rate</key><integer>44100</integer>
			<key>Release Date</key><date>2008-02-02T08:00:00Z</date>
			<key>Artwork Count</key><integer>1</integer>
			<key>Persistent ID</key><string>5F2804C9AD894F7B</string>
			<key>Track Type</key><string>File</string>
			<key>File Folder Count</key><integer>5</integer>
			<key>Library Folder Count</key><integer>1</integer>
			<key>Name</key><string>The Condos (Live)</string>
			<key>Artist</key><string>Iron Curtain</string>
			<key>Album</key><string>Desertion</string>
			<key>Genre</key><string>Darkwave</string>
			<key>Kind</key><string>MPEG audio file</string>
			<key>Sort Name</key><string>Condos (Live)</string>
			<key>Location</key><string>file:///Users/tonyfischetti/Music/iTunes/iTunes%20Media/Music/Iron%20Curtain/Desertion/12%20The%20Condos%20(Live).mp3</string>
		</dict>
		<key>29933</key>
		<dict>
			<key>Track ID</key><integer>29933</integer>
			<key>Size</key><integer>8347981</integer>
			<key>Total Time</key><integer>258351</integer>
			<key>Track Number</key><integer>1</integer>
			<key>Track Count</key><integer>9</integer>
			<key>Year</key><integer>1981</integer>
			<key>Date Modified</key><date>2013-10-19T04:44:21Z</date>
			<key>Date Added</key><date>2018-04-09T14:48:31Z</date>
			<key>Bit Rate</key><integer>256</integer>
			<key>Sample Rate</key><integer>44100</integer>
			<key>Artwork Count</key><integer>1</integer>
			<key>Persistent ID</key><string>ACB1E14D17097DCE</string>
			<key>Track Type</key><string>File</string>
			<key>File Folder Count</key><integer>5</integer>
			<key>Library Folder Count</key><integer>1</integer>
			<key>Name</key><string>Paris Tokyo</string>
			<key>Artist</key><string>Mathématiques Modernes</string>
			<key>Album Artist</key><string>Mathématiques Modernes</string>
			<key>Album</key><string>Les Visiteurs Du Soir</string>
			<key>Genre</key><string>Synth Pop</string>
			<key>Kind</key><string>MPEG audio file</string>
			<key>Location</key><string>file:///Users/tonyfischetti/Music/iTunes/iTunes%20Media/Music/Mathe%CC%81matiques%20Modernes/Les%20Visiteurs%20Du%20Soir/01%20Paris%20Tokyo.mp3</string>
		</dict>
		<key>29941</key>
		<dict>
			<key>Track ID</key><integer>29941</integer>
			<key>Size</key><integer>6663603</integer>
			<key>Total Time</key><integer>205714</integer>
			<key>Track Number</key><integer>2</integer>
			<key>Track Count</key><integer>9</integer>
			<key>Year</key><integer>1981</integer>
			<key>Date Modified</key><date>2013-10-19T04:44:21Z</date>
			<key>Date Added</key><date>2018-04-09T14:48:31Z</date>
			<key>Bit Rate</key><integer>256</integer>
			<key>Sample Rate</key><integer>44100</integer>
			<key>Artwork Count</key><integer>1</integer>
			<key>Persistent ID</key><string>625EEB610F3EA7A2</string>
			<key>Track Type</key><string>File</string>
			<key>File Folder Count</key><integer>5</integer>
			<key>Library Folder Count</key><integer>1</integer>
			<key>Name</key><string>TV Night</string>
			<key>Artist</key><string>Mathématiques Modernes</string>
			<key>Album Artist</key><string>Mathématiques Modernes</string>
			<key>Album</key><string>Les Visiteurs Du Soir</string>
			<key>Genre</key><string>Synth Pop</string>
			<key>Kind</key><string>MPEG audio file</string>
			<key>Location</key><string>file:///Users/tonyfischetti/Music/iTunes/iTunes%20Media/Music/Mathe%CC%81matiques%20Modernes/Les%20Visiteurs%20Du%20Soir/02%20TV%20Night.mp3</string>
		</dict>
		<key>29945</key>
		<dict>
			<key>Track ID</key><integer>29945</integer>
			<key>Size</key><integer>7790422</integer>
			<key>Total Time</key><integer>240927</integer>
			<key>Track Number</key><integer>3</integer>
			<key>Track Count</key><integer>9</integer>
			<key>Year</key><integer>1981</integer>
			<key>Date Modified</key><date>2013-10-19T04:44:22Z</date>
			<key>Date Added</key><date>2018-04-09T14:48:31Z</date>
			<key>Bit Rate</key><integer>256</integer>
			<key>Sample Rate</key><integer>44100</integer>
			<key>Artwork Count</key><integer>1</integer>
			<key>Persistent ID</key><string>6C4500A74C273344</string>
			<key>Track Type</key><string>File</string>
			<key>File Folder Count</key><integer>5</integer>
			<key>Library Folder Count</key><integer>1</integer>
			<key>Name</key><string>A + B = C</string>
			<key>Artist</key><string>Mathématiques Modernes</string>
			<key>Album Artist</key><string>Mathématiques Modernes</string>
			<key>Album</key><string>Les Visiteurs Du Soir</string>
			<key>Genre</key><string>Synth Pop</string>
			<key>Kind</key><string>MPEG audio file</string>
			<key>Sort Name</key><string>+ B = C</string>
			<key>Location</key><string>file:///Users/tonyfischetti/Music/iTunes/iTunes%20Media/Music/Mathe%CC%81matiques%20Modernes/Les%20Visiteurs%20Du%20Soir/03%20A%20+%20B%20=%20C.mp3</string>
		</dict>
		<key>29949</key>
		<dict>
			<key>Track ID</key><integer>29949</integer>
			<key>Size</key><integer>13980400</integer>
			<key>Total Time</key><integer>434364</integer>
			<key>Track Number</key><integer>4</integer>
			<key>Track Count</key><integer>9</integer>
			<key>Year</key><integer>1981</integer>
			<key>Date Modified</key><date>2013-10-19T04:44:22Z</date>
			<key>Date Added</key><date>2018-04-09T14:48:31Z</date>
			<key>Bit Rate</key><integer>256</integer>
			<key>Sample Rate</key><integer>44100</integer>
			<key>Artwork Count</key><integer>1</integer>
			<key>Persistent ID</key><string>76632121B3EDC37A</string>
			<key>Track Type</key><string>File</string>
			<key>File Folder Count</key><integer>5</integer>
			<key>Library Folder Count</key><integer>1</integer>
			<key>Name</key><string>Jungle Hurt</string>
			<key>Artist</key><string>Mathématiques Modernes</string>
			<key>Album Artist</key><string>Mathématiques Modernes</string>
			<key>Album</key><string>Les Visiteurs Du Soir</string>
			<key>Genre</key><string>Synth Pop</string>
			<key>Kind</key><string>MPEG audio file</string>
			<key>Location</key><string>file:///Users/tonyfischetti/Music/iTunes/iTunes%20Media/Music/Mathe%CC%81matiques%20Modernes/Les%20Visiteurs%20Du%20Soir/04%20Jungle%20Hurt.mp3</string>
		</dict>
		<key>29935</key>
		<dict>
			<key>Track ID</key><integer>29935</integer>
			<key>Size</key><integer>9368638</integer>
			<key>Total Time</key><integer>290246</integer>
			<key>Track Number</key><integer>5</integer>
			<key>Track Count</key><integer>9</integer>
			<key>Year</key><integer>1981</integer>
			<key>Date Modified</key><date>2013-10-19T04:44:23Z</date>
			<key>Date Added</key><date>2018-04-09T14:48:31Z</date>
			<key>Bit Rate</key><integer>256</integer>
			<key>Sample Rate</key><integer>44100</integer>
			<key>Artwork Count</key><integer>1</integer>
			<key>Persistent ID</key><string>BBD6948C5297461C</string>
			<key>Track Type</key><string>File</string>
			<key>File Folder Count</key><integer>5</integer>
			<key>Library Folder Count</key><integer>1</integer>
			<key>Name</key><string>Disco Rough</string>
			<key>Artist</key><string>Mathématiques Modernes</string>
			<key>Album Artist</key><string>Mathématiques Modernes</string>
			<key>Album</key><string>Les Visiteurs Du Soir</string>
			<key>Genre</key><string>Synth Pop</string>
			<key>Kind</key><string>MPEG audio file</string>
			<key>Location</key><string>file:///Users/tonyfischetti/Music/iTunes/iTunes%20Media/Music/Mathe%CC%81matiques%20Modernes/Les%20Visiteurs%20Du%20Soir/05%20Disco%20Rough.mp3</string>
		</dict>
		<key>29943</key>
		<dict>
			<key>Track ID</key><integer>29943</integer>
			<key>Size</key><integer>6522338</integer>
			<key>Total Time</key><integer>201299</integer>
			<key>Track Number</key><integer>6</integer>
			<key>Track Count</key><integer>9</integer>
			<key>Year</key><integer>1981</integer>
			<key>Date Modified</key><date>2013-10-19T04:44:23Z</date>
			<key>Date Added</key><date>2018-04-09T14:48:31Z</date>
			<key>Bit Rate</key><integer>256</integer>
			<key>Sample Rate</key><integer>44100</integer>
			<key>Artwork Count</key><integer>1</integer>
			<key>Persistent ID</key><string>D3AB2B0359A6DBE4</string>
			<key>Track Type</key><string>File</string>
			<key>File Folder Count</key><integer>5</integer>
			<key>Library Folder Count</key><integer>1</integer>
			<key>Name</key><string>Boy Be My Toy</string>
			<key>Artist</key><string>Mathématiques Modernes</string>
			<key>Album Artist</key><string>Mathématiques Modernes</string>
			<key>Album</key><string>Les Visiteurs Du Soir</string>
			<key>Genre</key><string>Synth Pop</string>
			<key>Kind</key><string>MPEG audio file</string>
			<key>Location</key><string>file:///Users/tonyfischetti/Music/iTunes/iTunes%20Media/Music/Mathe%CC%81matiques%20Modernes/Les%20Visiteurs%20Du%20Soir/06%20Boy%20Be%20My%20Toy.mp3</string>
		</dict>
		<key>29937</key>
		<dict>
			<key>Track ID</key><integer>29937</integer>
			<key>Size</key><integer>7942461</integer>
			<key>Total Time</key><integer>245681</integer>
			<key>Track Number</key><integer>7</integer>
			<key>Track Count</key><integer>9</integer>
			<key>Year</key><integer>1981</integer>
			<key>Date Modified</key><date>2013-10-19T04:44:23Z</date>
			<key>Date Added</key><date>2018-04-09T14:48:31Z</date>
			<key>Bit Rate</key><integer>256</integer>
			<key>Sample Rate</key><integer>44100</integer>
			<key>Artwork Count</key><integer>1</integer>
			<key>Persistent ID</key><string>905712B36CE15021</string>
			<key>Track Type</key><string>File</string>
			<key>File Folder Count</key><integer>5</integer>
			<key>Library Folder Count</key><integer>1</integer>
			<key>Name</key><string>Réponds-Moi</string>
			<key>Artist</key><string>Mathématiques Modernes</string>
			<key>Album Artist</key><string>Mathématiques Modernes</string>
			<key>Album</key><string>Les Visiteurs Du Soir</string>
			<key>Genre</key><string>Synth Pop</string>
			<key>Kind</key><string>MPEG audio file</string>
			<key>Location</key><string>file:///Users/tonyfischetti/Music/iTunes/iTunes%20Media/Music/Mathe%CC%81matiques%20Modernes/Les%20Visiteurs%20Du%20Soir/07%20Re%CC%81ponds-Moi.mp3</string>
		</dict>
		<key>29939</key>
		<dict>
			<key>Track ID</key><integer>29939</integer>
			<key>Size</key><integer>6641043</integer>
			<key>Total Time</key><integer>205008</integer>
			<key>Track Number</key><integer>8</integer>
			<key>Track Count</key><integer>9</integer>
			<key>Year</key><integer>1981</integer>
			<key>Date Modified</key><date>2013-10-19T04:44:23Z</date>
			<key>Date Added</key><date>2018-04-09T14:48:31Z</date>
			<key>Bit Rate</key><integer>256</integer>
			<key>Sample Rate</key><integer>44100</integer>
			<key>Artwork Count</key><integer>1</integer>
			<key>Persistent ID</key><string>4CA526AEB221F9AD</string>
			<key>Track Type</key><string>File</string>
			<key>File Folder Count</key><integer>5</integer>
			<key>Library Folder Count</key><integer>1</integer>
			<key>Name</key><string>Athletical Mystery</string>
			<key>Artist</key><string>Mathématiques Modernes</string>
			<key>Album Artist</key><string>Mathématiques Modernes</string>
			<key>Album</key><string>Les Visiteurs Du Soir</string>
			<key>Genre</key><string>Synth Pop</string>
			<key>Kind</key><string>MPEG audio file</string>
			<key>Location</key><string>file:///Users/tonyfischetti/Music/iTunes/iTunes%20Media/Music/Mathe%CC%81matiques%20Modernes/Les%20Visiteurs%20Du%20Soir/08%20Athletical%20Mystery.mp3</string>
		</dict>
		<key>29947</key>
		<dict>
			<key>Track ID</key><integer>29947</integer>
			<key>Size</key><integer>6509809</integer>
			<key>Total Time</key><integer>200907</integer>
			<key>Track Number</key><integer>9</integer>
			<key>Track Count</key><integer>9</integer>
			<key>Year</key><integer>1981</integer>
			<key>Date Modified</key><date>2013-10-19T04:44:24Z</date>
			<key>Date Added</key><date>2018-04-09T14:48:31Z</date>
			<key>Bit Rate</key><integer>256</integer>
			<key>Sample Rate</key><integer>44100</integer>
			<key>Artwork Count</key><integer>1</integer>
			<key>Persistent ID</key><string>BB4D4F204615392E</string>
			<key>Track Type</key><string>File</string>
			<key>File Folder Count</key><integer>5</integer>
			<key>Library Folder Count</key><integer>1</integer>
			<key>Name</key><string>TV Night (Instrumental)</string>
			<key>Artist</key><string>Mathématiques Modernes</string>
			<key>Album Artist</key><string>Mathématiques Modernes</string>
			<key>Album</key><string>Les Visiteurs Du Soir</string>
			<key>Genre</key><string>Synth Pop</string>
			<key>Kind</key><string>MPEG audio file</string>
			<key>Location</key><string>file:///Users/tonyfischetti/Music/iTunes/iTunes%20Media/Music/Mathe%CC%81matiques%20Modernes/Les%20Visiteurs%20Du%20Soir/09%20TV%20Night%20(Instrumental).mp3</string>
		</dict>
		<key>35007</key>
		<dict>
			<key>Track ID</key><integer>35007</integer>
			<key>Size</key><integer>6320314</integer>
			<key>Total Time</key><integer>261982</integer>
			<key>Track Number</key><integer>4</integer>
			<key>Track Count</key><integer>7</integer>
			<key>Year</key><integer>2008</integer>
			<key>Date Modified</key><date>2013-10-19T04:38:54Z</date>
			<key>Date Added</key><date>2018-04-09T14:48:31Z</date>
			<key>Bit Rate</key><integer>192</integer>
			<key>Sample Rate</key><integer>44100</integer>
			<key>Persistent ID</key><string>E2A3D2C8A9267A3F</string>
			<key>Track Type</key><string>File</string>
			<key>File Folder Count</key><integer>5</integer>
			<key>Library Folder Count</key><integer>1</integer>
			<key>Name</key><string>Acting Out</string>
			<key>Artist</key><string>Iron Curtain</string>
			<key>Album</key><string>Artifact</string>
			<key>Genre</key><string>Darkwave</string>
			<key>Kind</key><string>MPEG audio file</string>
			<key>Location</key><string>file:///Users/tonyfischetti/Music/iTunes/iTunes%20Media/Music/Iron%20Curtain/Artifact/04%20Acting%20Out.mp3</string>
		</dict>
		<key>35009</key>
		<dict>
			<key>Track ID</key><integer>35009</integer>
			<key>Size</key><integer>6528231</integer>
			<key>Total Time</key><integer>279013</integer>
			<key>Track Number</key><integer>3</integer>
			<key>Track Count</key><integer>7</integer>
			<key>Year</key><integer>2008</integer>
			<key>Date Modified</key><date>2013-10-19T04:38:54Z</date>
			<key>Date Added</key><date>2018-04-09T14:48:31Z</date>
			<key>Bit Rate</key><integer>187</integer>
			<key>Sample Rate</key><integer>44100</integer>
			<key>Persistent ID</key><string>0D0A536CF90D6DD5</string>
			<key>Track Type</key><string>File</string>
			<key>File Folder Count</key><integer>5</integer>
			<key>Library Folder Count</key><integer>1</integer>
			<key>Name</key><string>Black Gloves</string>
			<key>Artist</key><string>Iron Curtain</string>
			<key>Album</key><string>Artifact</string>
			<key>Genre</key><string>Darkwave</string>
			<key>Kind</key><string>MPEG audio file</string>
			<key>Location</key><string>file:///Users/tonyfischetti/Music/iTunes/iTunes%20Media/Music/Iron%20Curtain/Artifact/03%20Black%20Gloves.mp3</string>
		</dict>
		<key>35003</key>
		<dict>
			<key>Track ID</key><integer>35003</integer>
			<key>Size</key><integer>7442977</integer>
			<key>Total Time</key><integer>306677</integer>
			<key>Track Number</key><integer>7</integer>
			<key>Track Count</key><integer>7</integer>
			<key>Year</key><integer>2008</integer>
			<key>Date Modified</key><date>2013-10-19T04:38:55Z</date>
			<key>Date Added</key><date>2018-04-09T14:48:31Z</date>
			<key>Bit Rate</key><integer>194</integer>
			<key>Sample Rate</key><integer>44100</integer>
			<key>Persistent ID</key><string>3B86416E21AE0BFA</string>
			<key>Track Type</key><string>File</string>
			<key>File Folder Count</key><integer>5</integer>
			<key>Library Folder Count</key><integer>1</integer>
			<key>Name</key><string>The Condos</string>
			<key>Artist</key><string>Iron Curtain</string>
			<key>Album</key><string>Artifact</string>
			<key>Genre</key><string>Darkwave</string>
			<key>Kind</key><string>MPEG audio file</string>
			<key>Sort Name</key><string>Condos</string>
			<key>Location</key><string>file:///Users/tonyfischetti/Music/iTunes/iTunes%20Media/Music/Iron%20Curtain/Artifact/07%20The%20Condos.mp3</string>
		</dict>
		<key>34999</key>
		<dict>
			<key>Track ID</key><integer>34999</integer>
			<key>Size</key><integer>10595416</integer>
			<key>Total Time</key><integer>410383</integer>
			<key>Track Number</key><integer>6</integer>
			<key>Track Count</key><integer>7</integer>
			<key>Year</key><integer>2008</integer>
			<key>Date Modified</key><date>2013-10-19T04:38:55Z</date>
			<key>Date Added</key><date>2018-04-09T14:48:31Z</date>
			<key>Bit Rate</key><integer>206</integer>
			<key>Sample Rate</key><integer>44100</integer>
			<key>Persistent ID</key><string>FB806B5CFADEF797</string>
			<key>Track Type</key><string>File</string>
			<key>File Folder Count</key><integer>5</integer>
			<key>Library Folder Count</key><integer>1</integer>
			<key>Name</key><string>First Punk Wars</string>
			<key>Artist</key><string>Iron Curtain</string>
			<key>Album</key><string>Artifact</string>
			<key>Genre</key><string>Darkwave</string>
			<key>Kind</key><string>MPEG audio file</string>
			<key>Location</key><string>file:///Users/tonyfischetti/Music/iTunes/iTunes%20Media/Music/Iron%20Curtain/Artifact/06%20First%20Punk%20Wars.mp3</string>
		</dict>
		<key>35005</key>
		<dict>
			<key>Track ID</key><integer>35005</integer>
			<key>Size</key><integer>9915154</integer>
			<key>Total Time</key><integer>412160</integer>
			<key>Track Number</key><integer>5</integer>
			<key>Track Count</key><integer>7</integer>
			<key>Year</key><integer>2008</integer>
			<key>Date Modified</key><date>2013-10-19T04:38:55Z</date>
			<key>Date Added</key><date>2018-04-09T14:48:31Z</date>
			<key>Bit Rate</key><integer>192</integer>
			<key>Sample Rate</key><integer>44100</integer>
			<key>Persistent ID</key><string>65FF7B5F534CF5D3</string>
			<key>Track Type</key><string>File</string>
			<key>File Folder Count</key><integer>5</integer>
			<key>Library Folder Count</key><integer>1</integer>
			<key>Name</key><string>One December Day</string>
			<key>Artist</key><string>Iron Curtain</string>
			<key>Album</key><string>Artifact</string>
			<key>Genre</key><string>Darkwave</string>
			<key>Kind</key><string>MPEG audio file</string>
			<key>Location</key><string>file:///Users/tonyfischetti/Music/iTunes/iTunes%20Media/Music/Iron%20Curtain/Artifact/05%20One%20December%20Day.mp3</string>
		</dict>
		<key>35011</key>
		<dict>
			<key>Track ID</key><integer>35011</integer>
			<key>Size</key><integer>6130493</integer>
			<key>Total Time</key><integer>273867</integer>
			<key>Track Number</key><integer>2</integer>
			<key>Track Count</key><integer>7</integer>
			<key>Year</key><integer>2008</integer>
			<key>Date Modified</key><date>2013-10-19T04:38:53Z</date>
			<key>Date Added</key><date>2018-04-09T14:48:31Z</date>
			<key>Bit Rate</key><integer>179</integer>
			<key>Sample Rate</key><integer>44100</integer>
			<key>Persistent ID</key><string>99F67FDAF8E0ECA5</string>
			<key>Track Type</key><string>File</string>
			<key>File Folder Count</key><integer>5</integer>
			<key>Library Folder Count</key><integer>1</integer>
			<key>Name</key><string>Television Saved My Life</string>
			<key>Artist</key><string>Iron Curtain</string>
			<key>Album</key><string>Artifact</string>
			<key>Genre</key><string>Darkwave</string>
			<key>Kind</key><string>MPEG audio file</string>
			<key>Location</key><string>file:///Users/tonyfischetti/Music/iTunes/iTunes%20Media/Music/Iron%20Curtain/Artifact/02%20Television%20Saved%20My%20Life.mp3</string>
		</dict>
		<key>35001</key>
		<dict>
			<key>Track ID</key><integer>35001</integer>
			<key>Size</key><integer>8479781</integer>
			<key>Total Time</key><integer>334158</integer>
			<key>Track Number</key><integer>1</integer>
			<key>Track Count</key><integer>7</integer>
			<key>Year</key><integer>2008</integer>
			<key>Date Modified</key><date>2013-10-19T04:38:53Z</date>
			<key>Date Added</key><date>2018-04-09T14:48:31Z</date>
			<key>Bit Rate</key><integer>202</integer>
			<key>Sample Rate</key><integer>44100</integer>
			<key>Persistent ID</key><string>5500391B9337F79D</string>
			<key>Track Type</key><string>File</string>
			<key>File Folder Count</key><integer>5</integer>
			<key>Library Folder Count</key><integer>1</integer>
			<key>Name</key><string>Quiet Mind</string>
			<key>Artist</key><string>Iron Curtain</string>
			<key>Album</key><string>Artifact</string>
			<key>Genre</key><string>Darkwave</string>
			<key>Kind</key><string>MPEG audio file</string>
			<key>Location</key><string>file:///Users/tonyfischetti/Music/iTunes/iTunes%20Media/Music/Iron%20Curtain/Artifact/01%20Quiet%20Mind.mp3</string>
		</dict>
	</dict>
	<key>Playlists</key>
	<array>
		<dict>
			<key>Playlist ID</key><integer>132117</integer>
			<key>Playlist Persistent ID</key><string>EC76E62030C3DB7D</string>
			<key>All Items</key><true/>
			<key>Name</key><string>Cold and New</string>
			<key>Playlist Items</key>
			<array>
				<dict>
					<key>Track ID</key><integer>35377</integer>
				</dict>
				<dict>
					<key>Track ID</key><integer>35375</integer>
				</dict>
				<dict>
					<key>Track ID</key><integer>35393</integer>
				</dict>
				<dict>
					<key>Track ID</key><integer>35381</integer>
				</dict>
				<dict>
					<key>Track ID</key><integer>35397</integer>
				</dict>
				<dict>
					<key>Track ID</key><integer>35407</integer>
				</dict>
				<dict>
					<key>Track ID</key><integer>35401</integer>
				</dict>
				<dict>
					<key>Track ID</key><integer>35385</integer>
				</dict>
				<dict>
					<key>Track ID</key><integer>35389</integer>
				</dict>
				<dict>
					<key>Track ID</key><integer>35387</integer>
				</dict>
				<dict>
					<key>Track ID</key><integer>35379</integer>
				</dict>
				<dict>
					<key>Track ID</key><integer>35403</integer>
				</dict>
				<dict>
					<key>Track ID</key><integer>35391</integer>
				</dict>
				<dict>
					<key>Track ID</key><integer>28161</integer>
				</dict>
				<dict>
					<key>Track ID</key><integer>28169</integer>
				</dict>
				<dict>
					<key>Track ID</key><integer>28155</integer>
				</dict>
				<dict>
					<key>Track ID</key><integer>28157</integer>
				</dict>
				<dict>
					<key>Track ID</key><integer>28163</integer>
				</dict>
				<dict>
					<key>Track ID</key><integer>28165</integer>
				</dict>
				<dict>
					<key>Track ID</key><integer>28159</integer>
				</dict>
				<dict>
					<key>Track ID</key><integer>28167</integer>
				</dict>
				<dict>
					<key>Track ID</key><integer>49255</integer>
				</dict>
				<dict>
					<key>Track ID</key><integer>35467</integer>
				</dict>
				<dict>
					<key>Track ID</key><integer>35475</integer>
				</dict>
				<dict>
					<key>Track ID</key><integer>35473</integer>
				</dict>
				<dict>
					<key>Track ID</key><integer>35485</integer>
				</dict>
				<dict>
					<key>Track ID</key><integer>35489</integer>
				</dict>
				<dict>
					<key>Track ID</key><integer>35479</integer>
				</dict>
				<dict>
					<key>Track ID</key><integer>35463</integer>
				</dict>
				<dict>
					<key>Track ID</key><integer>35487</integer>
				</dict>
				<dict>
					<key>Track ID</key><integer>35491</integer>
				</dict>
				<dict>
					<key>Track ID</key><integer>35481</integer>
				</dict>
				<dict>
					<key>Track ID</key><integer>35483</integer>
				</dict>
				<dict>
					<key>Track ID</key><integer>35471</integer>
				</dict>
				<dict>
					<key>Track ID</key><integer>35477</integer>
				</dict>
				<dict>
					<key>Track ID</key><integer>35465</integer>
				</dict>
				<dict>
					<key>Track ID</key><integer>35469</integer>
				</dict>
				<dict>
					<key>Track ID</key><integer>34985</integer>
				</dict>
				<dict>
					<key>Track ID</key><integer>34975</integer>
				</dict>
				<dict>
					<key>Track ID</key><integer>34977</integer>
				</dict>
				<dict>
					<key>Track ID</key><integer>34993</integer>
				</dict>
				<dict>
					<key>Track ID</key><integer>34983</integer>
				</dict>
				<dict>
					<key>Track ID</key><integer>34981</integer>
				</dict>
				<dict>
					<key>Track ID</key><integer>34979</integer>
				</dict>
				<dict>
					<key>Track ID</key><integer>34987</integer>
				</dict>
				<dict>
					<key>Track ID</key><integer>34997</integer>
				</dict>
				<dict>
					<key>Track ID</key><integer>34991</integer>
				</dict>
				<dict>
					<key>Track ID</key><integer>34989</integer>
				</dict>
				<dict>
					<key>Track ID</key><integer>34995</integer>
				</dict>
				<dict>
					<key>Track ID</key><integer>29933</integer>
				</dict>
				<dict>
					<key>Track ID</key><integer>29941</integer>
				</dict>
				<dict>
					<key>Track ID</key><integer>29945</integer>
				</dict>
				<dict>
					<key>Track ID</key><integer>29949</integer>
				</dict>
				<dict>
					<key>Track ID</key><integer>29935</integer>
				</dict>
				<dict>
					<key>Track ID</key><integer>29943</integer>
				</dict>
				<dict>
					<key>Track ID</key><integer>29937</integer>
				</dict>
				<dict>
					<key>Track ID</key><integer>29939</integer>
				</dict>
				<dict>
					<key>Track ID</key><integer>29947</integer>
				</dict>
				<dict>
					<key>Track ID</key><integer>35007</integer>
				</dict>
				<dict>
					<key>Track ID</key><integer>35009</integer>
				</dict>
				<dict>
					<key>Track ID</key><integer>35003</integer>
				</dict>
				<dict>
					<key>Track ID</key><integer>34999</integer>
				</dict>
				<dict>
					<key>Track ID</key><integer>35005</integer>
				</dict>
				<dict>
					<key>Track ID</key><integer>35011</integer>
				</dict>
				<dict>
					<key>Track ID</key><integer>35001</integer>
				</dict>
			</array>
		</dict>
	</array>
</dict>
</plist>