<?xml version="1.0" encoding="UTF-8"?>
<!DOCTYPE plist PUBLIC "-//Apple Computer//DTD PLIST 1.0//EN" "http://www.apple.com/DTDs/PropertyList-1.0.dtd">
<plist version="1.0">
<dict>
	<key>Tracks</key>
	<dict>
		<key>12328</key>
		<dict>
			<key>Track ID</key><integer>12328</integer>
			<key>Size</key><integer>6349584</integer>
			<key>Total Time</key><integer>182857</integer>
			<key>Disc Number</key><integer>1</integer>
			<key>Disc Count</key><integer>1</integer>
			<key>Track Number</key><integer>1</integer>
			<key>Track Count</key><integer>16</integer>
			<key>Year</key><integer>1997</integer>
			<key>Date Modified</key><date>2013-10-19T05:05:23Z</date>
			<key>Date Added</key><date>2018-04-09T14:48:31Z</date>
			<key>Bit Rate</key><integer>264</integer>
			<key>Sample Rate</key><integer>44100</integer>
			<key>Play Count</key><integer>1</integer>
			<key>Play Date</key><integer>3647418433</integer>
			<key>Play Date UTC</key><date>2019-07-31T15:47:13Z</date>
			<key>Artwork Count</key><integer>1</integer>
			<key>Persistent ID</key><string>85314E9F0A5D6DEA</string>
			<key>Track Type</key><string>File</string>
			<key>File Folder Count</key><integer>5</integer>
			<key>Library Folder Count</key><integer>1</integer>
			<key>Name</key><string>Super Rad!</string>
			<key>Artist</key><string>The Aquabats</string>
			<key>Album</key><string>The Fury Of The Aquabats!</string>
			<key>Genre</key><string>Ska</string>
			<key>Kind</key><string>MPEG audio file</string>
			<key>Sort Album</key><string>Fury Of The Aquabats!</string>
			<key>Sort Artist</key><string>Aquabats</string>
			<key>Location</key><string>file:///Users/tonyfischetti/Music/iTunes/iTunes%20Media/Music/The%20Aquabats/The%20Fury%20Of%20The%20Aquabats!/01%20Super%20Rad!.mp3</string>
		</dict>
		<key>12330</key>
		<dict>
			<key>Track ID</key><integer>12330</integer>
			<key>Size</key><integer>4078936</integer>
			<key>Total Time</key><integer>120920</integer>
			<key>Disc Number</key><integer>1</integer>
			<key>Disc Count</key><integer>1</integer>
			<key>Track Number</key><integer>10</integer>
			<key>Track Count</key><integer>16</integer>
			<key>Year</key><integer>1997</integer>
			<key>Date Modified</key><date>2013-10-19T05:05:26Z</date>
			<key>Date Added</key><date>2018-04-09T14:48:31Z</date>
			<key>Bit Rate</key><integer>249</integer>
			<key>Sample Rate</key><integer>44100</integer>
			<key>Play Count</key><integer>1</integer>
			<key>Play Date</key><integer>3647418728</integer>
			<key>Play Date UTC</key><date>2019-07-31T15:52:08Z</date>
			<key>Artwork Count</key><integer>1</integer>
			<key>Persistent ID</key><string>0A8D56786DE35D92</string>
			<key>Track Type</key><string>File</string>
			<key>File Folder Count</key><integer>5</integer>
			<key>Library Folder Count</key><integer>1</integer>
			<key>Name</key><string>Idiot Box!</string>
			<key>Artist</key><string>The Aquabats</string>
			<key>Album</key><string>The Fury Of The Aquabats!</string>
			<key>Genre</key><string>Ska</string>
			<key>Kind</key><string>MPEG audio file</string>
			<key>Sort Album</key><string>Fury Of The Aquabats!</string>
			<key>Sort Artist</key><string>Aquabats</string>
			<key>Location</key><string>file:///Users/tonyfischetti/Music/iTunes/iTunes%20Media/Music/The%20Aquabats/The%20Fury%20Of%20The%20Aquabats!/10%20Idiot%20Box!.mp3</string>
		</dict>
		<key>13580</key>
		<dict>
			<key>Track ID</key><integer>13580</integer>
			<key>Size</key><integer>3835808</integer>
			<key>Total Time</key><integer>159634</integer>
			<key>Disc Number</key><integer>1</integer>
			<key>Disc Count</key><integer>1</integer>
			<key>Track Number</key><integer>5</integer>
			<key>Year</key><integer>2002</integer>
			<key>Date Modified</key><date>2013-10-19T04:10:30Z</date>
			<key>Date Added</key><date>2018-04-09T14:48:31Z</date>
			<key>Bit Rate</key><integer>192</integer>
			<key>Sample Rate</key><integer>44100</integer>
			<key>Persistent ID</key><string>8009475D98AD79FD</string>
			<key>Track Type</key><string>File</string>
			<key>File Folder Count</key><integer>5</integer>
			<key>Library Folder Count</key><integer>1</integer>
			<key>Name</key><string>What Goes Around Comes Around</string>
			<key>Artist</key><string>Catch 22</string>
			<key>Album Artist</key><string>Catch 22</string>
			<key>Composer</key><string>Jeff Davidson/Ryan Eldred</string>
			<key>Album</key><string>Alone in a Crowd</string>
			<key>Genre</key><string>Ska</string>
			<key>Kind</key><string>MPEG audio file</string>
			<key>Comments</key><string>0</string>
			<key>Location</key><string>file:///Users/tonyfischetti/Music/iTunes/iTunes%20Media/Music/Catch%2022/Alone%20in%20a%20Crowd/05%20What%20Goes%20Around%20Comes%20Around.mp3</string>
		</dict>
		<key>13572</key>
		<dict>
			<key>Track ID</key><integer>13572</integer>
			<key>Size</key><integer>3636839</integer>
			<key>Total Time</key><integer>151327</integer>
			<key>Track Number</key><integer>1</integer>
			<key>Year</key><integer>1998</integer>
			<key>Date Modified</key><date>2013-10-19T04:10:34Z</date>
			<key>Date Added</key><date>2018-04-09T14:48:31Z</date>
			<key>Bit Rate</key><integer>192</integer>
			<key>Sample Rate</key><integer>44100</integer>
			<key>Persistent ID</key><string>05A9DF914B685944</string>
			<key>Track Type</key><string>File</string>
			<key>File Folder Count</key><integer>5</integer>
			<key>Library Folder Count</key><integer>1</integer>
			<key>Name</key><string>Dear Sergio</string>
			<key>Artist</key><string>Catch 22</string>
			<key>Album Artist</key><string>Catch 22</string>
			<key>Composer</key><string>Tomas Kalnoky</string>
			<key>Album</key><string>Keasbey Nights</string>
			<key>Genre</key><string>Ska</string>
			<key>Kind</key><string>MPEG audio file</string>
			<key>Comments</key><string>0</string>
			<key>Location</key><string>file:///Users/tonyfischetti/Music/iTunes/iTunes%20Media/Music/Catch%2022/Keasbey%20Nights/01%20Dear%20Sergio.mp3</string>
		</dict>
		<key>13556</key>
		<dict>
			<key>Track ID</key><integer>13556</integer>
			<key>Size</key><integer>3401739</integer>
			<key>Total Time</key><integer>141531</integer>
			<key>Track Number</key><integer>2</integer>
			<key>Year</key><integer>1998</integer>
			<key>Date Modified</key><date>2013-10-19T04:10:34Z</date>
			<key>Date Added</key><date>2018-04-09T14:48:31Z</date>
			<key>Bit Rate</key><integer>192</integer>
			<key>Sample Rate</key><integer>44100</integer>
			<key>Persistent ID</key><string>CF1C3D741064A780</string>
			<key>Track Type</key><string>File</string>
			<key>File Folder Count</key><integer>5</integer>
			<key>Library Folder Count</key><integer>1</integer>
			<key>Name</key><string>Sick and Sad</string>
			<key>Artist</key><string>Catch 22</string>
			<key>Album Artist</key><string>Catch 22</string>
			<key>Composer</key><string>Tomas Kalnoky</string>
			<key>Album</key><string>Keasbey Nights</string>
			<key>Genre</key><string>Ska</string>
			<key>Kind</key><string>MPEG audio file</string>
			<key>Comments</key><string>0</string>
			<key>Location</key><string>file:///Users/tonyfischetti/Music/iTunes/iTunes%20Media/Music/Catch%2022/Keasbey%20Nights/02%20Sick%20and%20Sad.mp3</string>
		</dict>
		<key>13564</key>
		<dict>
			<key>Track ID</key><integer>13564</integer>
			<key>Size</key><integer>4396068</integer>
			<key>Total Time</key><integer>182961</integer>
			<key>Track Number</key><integer>3</integer>
			<key>Year</key><integer>1998</integer>
			<key>Date Modified</key><date>2013-10-19T04:10:34Z</date>
			<key>Date Added</key><date>2018-04-09T14:48:31Z</date>
			<key>Bit Rate</key><integer>192</integer>
			<key>Sample Rate</key><integer>44100</integer>
			<key>Persistent ID</key><string>F2310F7330330E4C</string>
			<key>Track Type</key><string>File</string>
			<key>File Folder Count</key><integer>5</integer>
			<key>Library Folder Count</key><integer>1</integer>
			<key>Name</key><string>Keasbey Nights</string>
			<key>Artist</key><string>Catch 22</string>
			<key>Album Artist</key><string>Catch 22</string>
			<key>Composer</key><string>Tomas Kalnoky</string>
			<key>Album</key><string>Keasbey Nights</string>
			<key>Genre</key><string>Ska</string>
			<key>Kind</key><string>MPEG audio file</string>
			<key>Comments</key><string>0 </string>
			<key>Location</key><string>file:///Users/tonyfischetti/Music/iTunes/iTunes%20Media/Music/Catch%2022/Keasbey%20Nights/03%20Keasbey%20Nights.mp3</string>
		</dict>
		<key>13576</key>
		<dict>
			<key>Track ID</key><integer>13576</integer>
			<key>Size</key><integer>7460579</integer>
			<key>Total Time</key><integer>310648</integer>
			<key>Track Number</key><integer>12</integer>
			<key>Year</key><integer>1998</integer>
			<key>Date Modified</key><date>2013-10-19T04:10:35Z</date>
			<key>Date Added</key><date>2018-04-09T14:48:31Z</date>
			<key>Bit Rate</key><integer>192</integer>
			<key>Sample Rate</key><integer>44100</integer>
			<key>Persistent ID</key><string>B7E8CA461689EE75</string>
			<key>Track Type</key><string>File</string>
			<key>File Folder Count</key><integer>5</integer>
			<key>Library Folder Count</key><integer>1</integer>
			<key>Name</key><string>Kristina She Don't Know I Exist</string>
			<key>Artist</key><string>Catch 22</string>
			<key>Album Artist</key><string>Catch 22</string>
			<key>Composer</key><string>Tomas Kalnoky</string>
			<key>Album</key><string>Keasbey Nights</string>
			<key>Genre</key><string>Ska</string>
			<key>Kind</key><string>MPEG audio file</string>
			<key>Comments</key><string>0</string>
			<key>Location</key><string>file:///Users/tonyfischetti/Music/iTunes/iTunes%20Media/Music/Catch%2022/Keasbey%20Nights/12%20Kristina%20She%20Don't%20Know%20I%20Exist.mp3</string>
		</dict>
		<key>7092</key>
		<dict>
			<key>Track ID</key><integer>7092</integer>
			<key>Size</key><integer>3653518</integer>
			<key>Total Time</key><integer>179644</integer>
			<key>Track Number</key><integer>2</integer>
			<key>Date Modified</key><date>2019-12-29T15:48:53Z</date>
			<key>Date Added</key><date>2018-04-09T14:48:31Z</date>
			<key>Bit Rate</key><integer>160</integer>
			<key>Sample Rate</key><integer>44100</integer>
			<key>Artwork Count</key><integer>1</integer>
			<key>Persistent ID</key><string>65C53A051F0E2F51</string>
			<key>Track Type</key><string>File</string>
			<key>File Folder Count</key><integer>-1</integer>
			<key>Library Folder Count</key><integer>-1</integer>
			<key>Name</key><string>You Never Asked Me To</string>
			<key>Artist</key><string>I Voted For Kodos</string>
			<key>Album</key><string>Close Enough For Ska</string>
			<key>Genre</key><string>Ska</string>
			<key>Kind</key><string>MPEG audio file</string>
			<key>Location</key><string>file:///Users/tonyfischetti/Dropbox/music/I%20Voted%20For%20Kodos/Close%20Enough%20For%20Ska/02%20You%20Never%20Asked%20Me%20To.mp3</string>
		</dict>
		<key>50924</key>
		<dict>
			<key>Track ID</key><integer>50924</integer>
			<key>Size</key><integer>5365888</integer>
			<key>Total Time</key><integer>134112</integer>
			<key>Track Number</key><integer>1</integer>
			<key>Year</key><integer>1997</integer>
			<key>Date Modified</key><date>2013-10-19T05:13:55Z</date>
			<key>Date Added</key><date>2018-04-09T14:48:31Z</date>
			<key>Bit Rate</key><integer>320</integer>
			<key>Sample Rate</key><integer>44100</integer>
			<key>Play Count</key><integer>1</integer>
			<key>Play Date</key><integer>3647419628</integer>
			<key>Play Date UTC</key><date>2019-07-31T16:07:08Z</date>
			<key>Persistent ID</key><string>23772C7FD8458152</string>
			<key>Track Type</key><string>File</string>
			<key>File Folder Count</key><integer>5</integer>
			<key>Library Folder Count</key><integer>1</integer>
			<key>Name</key><string>Noise Brigade</string>
			<key>Artist</key><string>The Mighty Mighty Bosstones</string>
			<key>Album</key><string>Let's Face It</string>
			<key>Genre</key><string>Ska</string>
			<key>Kind</key><string>MPEG audio file</string>
			<key>Sort Artist</key><string>Mighty Mighty Bosstones</string>
			<key>Location</key><string>file:///Users/tonyfischetti/Music/iTunes/iTunes%20Media/Music/The%20Mighty%20Mighty%20Bosstones/Let's%20Face%20It/01%20Noise%20Brigade.mp3</string>
		</dict>
		<key>50928</key>
		<dict>
			<key>Track ID</key><integer>50928</integer>
			<key>Size</key><integer>6646872</integer>
			<key>Total Time</key><integer>166138</integer>
			<key>Track Number</key><integer>2</integer>
			<key>Year</key><integer>1997</integer>
			<key>Date Modified</key><date>2013-10-19T05:13:55Z</date>
			<key>Date Added</key><date>2018-04-09T14:48:31Z</date>
			<key>Bit Rate</key><integer>320</integer>
			<key>Sample Rate</key><integer>44100</integer>
			<key>Play Count</key><integer>1</integer>
			<key>Play Date</key><integer>3647419888</integer>
			<key>Play Date UTC</key><date>2019-07-31T16:11:28Z</date>
			<key>Persistent ID</key><string>87823C68B08BCCC7</string>
			<key>Track Type</key><string>File</string>
			<key>File Folder Count</key><integer>5</integer>
			<key>Library Folder Count</key><integer>1</integer>
			<key>Name</key><string>The Rascal King</string>
			<key>Artist</key><string>The Mighty Mighty Bosstones</string>
			<key>Album</key><string>Let's Face It</string>
			<key>Genre</key><string>Ska</string>
			<key>Kind</key><string>MPEG audio file</string>
			<key>Sort Name</key><string>Rascal King</string>
			<key>Sort Artist</key><string>Mighty Mighty Bosstones</string>
			<key>Location</key><string>file:///Users/tonyfischetti/Music/iTunes/iTunes%20Media/Music/The%20Mighty%20Mighty%20Bosstones/Let's%20Face%20It/02%20The%20Rascal%20King.mp3</string>
		</dict>
		<key>50940</key>
		<dict>
			<key>Track ID</key><integer>50940</integer>
			<key>Size</key><integer>6447232</integer>
			<key>Total Time</key><integer>161123</integer>
			<key>Track Number</key><integer>12</integer>
			<key>Year</key><integer>1997</integer>
			<key>Date Modified</key><date>2013-10-19T05:13:58Z</date>
			<key>Date Added</key><date>2018-04-09T14:48:31Z</date>
			<key>Bit Rate</key><integer>320</integer>
			<key>Sample Rate</key><integer>44100</integer>
			<key>Play Count</key><integer>1</integer>
			<key>Play Date</key><integer>3647422587</integer>
			<key>Play Date UTC</key><date>2019-07-31T16:56:27Z</date>
			<key>Persistent ID</key><string>0DDA2EE80DB07A53</string>
			<key>Track Type</key><string>File</string>
			<key>File Folder Count</key><integer>5</integer>
			<key>Library Folder Count</key><integer>1</integer>
			<key>Name</key><string>1-2-8</string>
			<key>Artist</key><string>The Mighty Mighty Bosstones</string>
			<key>Album</key><string>Let's Face It</string>
			<key>Genre</key><string>Ska</string>
			<key>Kind</key><string>MPEG audio file</string>
			<key>Sort Artist</key><string>Mighty Mighty Bosstones</string>
			<key>Location</key><string>file:///Users/tonyfischetti/Music/iTunes/iTunes%20Media/Music/The%20Mighty%20Mighty%20Bosstones/Let's%20Face%20It/12%201-2-8.mp3</string>
		</dict>
		<key>51002</key>
		<dict>
			<key>Track ID</key><integer>51002</integer>
			<key>Size</key><integer>7368832</integer>
			<key>Total Time</key><integer>184189</integer>
			<key>Track Number</key><integer>3</integer>
			<key>Date Modified</key><date>2013-10-19T05:13:59Z</date>
			<key>Date Added</key><date>2018-04-09T14:48:31Z</date>
			<key>Bit Rate</key><integer>320</integer>
			<key>Sample Rate</key><integer>44100</integer>
			<key>Persistent ID</key><string>8FEF41A4BBE550BD</string>
			<key>Track Type</key><string>File</string>
			<key>File Folder Count</key><integer>5</integer>
			<key>Library Folder Count</key><integer>1</integer>
			<key>Name</key><string>He's Back</string>
			<key>Artist</key><string>The Mighty Mighty Bosstones</string>
			<key>Album</key><string>Live From the Middle East</string>
			<key>Genre</key><string>Ska</string>
			<key>Kind</key><string>MPEG audio file</string>
			<key>Sort Artist</key><string>Mighty Mighty Bosstones</string>
			<key>Location</key><string>file:///Users/tonyfischetti/Music/iTunes/iTunes%20Media/Music/The%20Mighty%20Mighty%20Bosstones/Live%20From%20the%20Middle%20East/03%20He's%20Back.mp3</string>
		</dict>
		<key>50830</key>
		<dict>
			<key>Track ID</key><integer>50830</integer>
			<key>Size</key><integer>8459708</integer>
			<key>Total Time</key><integer>206889</integer>
			<key>Track Number</key><integer>2</integer>
			<key>Year</key><integer>1992</integer>
			<key>Date Modified</key><date>2019-12-29T16:02:17Z</date>
			<key>Date Added</key><date>2018-04-09T14:48:31Z</date>
			<key>Bit Rate</key><integer>320</integer>
			<key>Sample Rate</key><integer>44100</integer>
			<key>Artwork Count</key><integer>1</integer>
			<key>Persistent ID</key><string>5F26D2446A3CE474</string>
			<key>Track Type</key><string>File</string>
			<key>File Folder Count</key><integer>-1</integer>
			<key>Library Folder Count</key><integer>-1</integer>
			<key>Name</key><string>Where'd You Go</string>
			<key>Artist</key><string>The Mighty Mighty Bosstones</string>
			<key>Album</key><string>More Noise and Other Disturbances</string>
			<key>Genre</key><string>Ska</string>
			<key>Kind</key><string>MPEG audio file</string>
			<key>Sort Artist</key><string>Mighty Mighty Bosstones</string>
			<key>Location</key><string>file:///Users/tonyfischetti/Dropbox/music/The%20Mighty%20Mighty%20Bosstones/More%20Noise%20and%20Other%20Disturbances/02%20Where'd%20You%20Go.mp3</string>
		</dict>
		<key>50838</key>
		<dict>
			<key>Track ID</key><integer>50838</integer>
			<key>Size</key><integer>8454777</integer>
			<key>Total Time</key><integer>206942</integer>
			<key>Track Number</key><integer>1</integer>
			<key>Year</key><integer>1993</integer>
			<key>Date Modified</key><date>2019-12-29T16:02:18Z</date>
			<key>Date Added</key><date>2018-04-09T14:48:31Z</date>
			<key>Bit Rate</key><integer>320</integer>
			<key>Sample Rate</key><integer>44100</integer>
			<key>Artwork Count</key><integer>1</integer>
			<key>Persistent ID</key><string>5B6C90CBC7B07920</string>
			<key>Track Type</key><string>File</string>
			<key>File Folder Count</key><integer>-1</integer>
			<key>Library Folder Count</key><integer>-1</integer>
			<key>Name</key><string>Someday I Suppose</string>
			<key>Artist</key><string>The Mighty Mighty Bosstones</string>
			<key>Album</key><string>Ska-Core, The Devil and More</string>
			<key>Genre</key><string>Ska</string>
			<key>Kind</key><string>MPEG audio file</string>
			<key>Sort Artist</key><string>Mighty Mighty Bosstones</string>
			<key>Location</key><string>file:///Users/tonyfischetti/Dropbox/music/The%20Mighty%20Mighty%20Bosstones/Ska-Core,%20The%20Devil%20and%20More/01%20Someday%20I%20Suppose.mp3</string>
		</dict>
		<key>44140</key>
		<dict>
			<key>Track ID</key><integer>44140</integer>
			<key>Size</key><integer>4127461</integer>
			<key>Total Time</key><integer>164597</integer>
			<key>Track Number</key><integer>1</integer>
			<key>Year</key><integer>1993</integer>
			<key>Date Modified</key><date>2013-10-19T04:47:02Z</date>
			<key>Date Added</key><date>2018-04-09T14:48:31Z</date>
			<key>Bit Rate</key><integer>192</integer>
			<key>Sample Rate</key><integer>44100</integer>
			<key>Artwork Count</key><integer>1</integer>
			<key>Persistent ID</key><string>423D08AF4399C5F3</string>
			<key>Track Type</key><string>File</string>
			<key>File Folder Count</key><integer>5</integer>
			<key>Library Folder Count</key><integer>1</integer>
			<key>Name</key><string>Skank by Numbers</string>
			<key>Artist</key><string>Mustard Plug</string>
			<key>Album</key><string>Big Daddy Multitude</string>
			<key>Genre</key><string>Ska</string>
			<key>Kind</key><string>MPEG audio file</string>
			<key>Comments</key><string>0</string>
			<key>Location</key><string>file:///Users/tonyfischetti/Music/iTunes/iTunes%20Media/Music/Mustard%20Plug/Big%20Daddy%20Multitude/01%20Skank%20by%20Numbers.mp3</string>
		</dict>
		<key>44152</key>
		<dict>
			<key>Track ID</key><integer>44152</integer>
			<key>Size</key><integer>2631972</integer>
			<key>Total Time</key><integer>102269</integer>
			<key>Track Number</key><integer>13</integer>
			<key>Year</key><integer>1993</integer>
			<key>Date Modified</key><date>2013-10-19T04:47:05Z</date>
			<key>Date Added</key><date>2018-04-09T14:48:31Z</date>
			<key>Bit Rate</key><integer>192</integer>
			<key>Sample Rate</key><integer>44100</integer>
			<key>Play Count</key><integer>1</integer>
			<key>Play Date</key><integer>3640840677</integer>
			<key>Play Date UTC</key><date>2019-05-16T12:37:57Z</date>
			<key>Artwork Count</key><integer>1</integer>
			<key>Persistent ID</key><string>3183BF65B577087E</string>
			<key>Track Type</key><string>File</string>
			<key>File Folder Count</key><integer>5</integer>
			<key>Library Folder Count</key><integer>1</integer>
			<key>Name</key><string>Brain on Ska</string>
			<key>Artist</key><string>Mustard Plug</string>
			<key>Album Artist</key><string>Mustard Plug</string>
			<key>Composer</key><string>Mustard Plug</string>
			<key>Album</key><string>Big Daddy Multitude</string>
			<key>Genre</key><string>Ska</string>
			<key>Kind</key><string>MPEG audio file</string>
			<key>Comments</key><string>0</string>
			<key>Location</key><string>file:///Users/tonyfischetti/Music/iTunes/iTunes%20Media/Music/Mustard%20Plug/Big%20Daddy%20Multitude/13%20Brain%20on%20Ska.mp3</string>
		</dict>
		<key>44154</key>
		<dict>
			<key>Track ID</key><integer>44154</integer>
			<key>Size</key><integer>4139126</integer>
			<key>Total Time</key><integer>165067</integer>
			<key>Track Number</key><integer>4</integer>
			<key>Year</key><integer>1993</integer>
			<key>Date Modified</key><date>2013-10-19T04:47:03Z</date>
			<key>Date Added</key><date>2018-04-09T14:48:31Z</date>
			<key>Bit Rate</key><integer>192</integer>
			<key>Sample Rate</key><integer>44100</integer>
			<key>Artwork Count</key><integer>1</integer>
			<key>Persistent ID</key><string>D1092F2761106E1C</string>
			<key>Track Type</key><string>File</string>
			<key>File Folder Count</key><integer>5</integer>
			<key>Library Folder Count</key><integer>1</integer>
			<key>Name</key><string>Mr. Smiley</string>
			<key>Artist</key><string>Mustard Plug</string>
			<key>Album Artist</key><string>Mustard Plug</string>
			<key>Composer</key><string>Mustard Plug</string>
			<key>Album</key><string>Big Daddy Multitude</string>
			<key>Genre</key><string>Ska</string>
			<key>Kind</key><string>MPEG audio file</string>
			<key>Comments</key><string>0</string>
			<key>Location</key><string>file:///Users/tonyfischetti/Music/iTunes/iTunes%20Media/Music/Mustard%20Plug/Big%20Daddy%20Multitude/04%20Mr.%20Smiley.mp3</string>
		</dict>
		<key>44202</key>
		<dict>
			<key>Track ID</key><integer>44202</integer>
			<key>Size</key><integer>5301226</integer>
			<key>Total Time</key><integer>220786</integer>
			<key>Track Number</key><integer>12</integer>
			<key>Year</key><integer>2006</integer>
			<key>Date Modified</key><date>2013-10-19T04:47:08Z</date>
			<key>Date Added</key><date>2018-04-09T14:48:31Z</date>
			<key>Bit Rate</key><integer>192</integer>
			<key>Sample Rate</key><integer>44100</integer>
			<key>Persistent ID</key><string>7B7B154297E0A9B0</string>
			<key>Track Type</key><string>File</string>
			<key>File Folder Count</key><integer>5</integer>
			<key>Library Folder Count</key><integer>1</integer>
			<key>Name</key><string>Beer</string>
			<key>Artist</key><string>Mustard Plug</string>
			<key>Album Artist</key><string>Mustard Plug</string>
			<key>Album</key><string>Evildoers Beware!</string>
			<key>Genre</key><string>Ska</string>
			<key>Kind</key><string>MPEG audio file</string>
			<key>Comments</key><string> 00000000 00000210 000007F0 0000000000948800 00000000 0050C730 00000000 00000000 00000000 00000000 00000000 00000000</string>
			<key>Location</key><string>file:///Users/tonyfischetti/Music/iTunes/iTunes%20Media/Music/Mustard%20Plug/Evildoers%20Beware!/12%20Beer.mp3</string>
		</dict>
		<key>44210</key>
		<dict>
			<key>Track ID</key><integer>44210</integer>
			<key>Size</key><integer>4535206</integer>
			<key>Total Time</key><integer>174811</integer>
			<key>Track Number</key><integer>7</integer>
			<key>Year</key><integer>2002</integer>
			<key>Date Modified</key><date>2013-10-19T04:47:12Z</date>
			<key>Date Added</key><date>2018-04-09T14:48:31Z</date>
			<key>Bit Rate</key><integer>192</integer>
			<key>Sample Rate</key><integer>44100</integer>
			<key>Artwork Count</key><integer>1</integer>
			<key>Persistent ID</key><string>B28CF2623DFE31D6</string>
			<key>Track Type</key><string>File</string>
			<key>File Folder Count</key><integer>5</integer>
			<key>Library Folder Count</key><integer>1</integer>
			<key>Name</key><string>Just a Minute</string>
			<key>Artist</key><string>Mustard Plug</string>
			<key>Album Artist</key><string>Mustard Plug</string>
			<key>Composer</key><string>Mustard Plug</string>
			<key>Album</key><string>Yellow #5</string>
			<key>Genre</key><string>Ska</string>
			<key>Kind</key><string>MPEG audio file</string>
			<key>Comments</key><string>0</string>
			<key>Location</key><string>file:///Users/tonyfischetti/Music/iTunes/iTunes%20Media/Music/Mustard%20Plug/Yellow%20%235/07%20Just%20a%20Minute.mp3</string>
		</dict>
		<key>43430</key>
		<dict>
			<key>Track ID</key><integer>43430</integer>
			<key>Size</key><integer>3430702</integer>
			<key>Total Time</key><integer>210599</integer>
			<key>Track Number</key><integer>6</integer>
			<key>Year</key><integer>1996</integer>
			<key>Date Modified</key><date>2019-12-30T04:20:30Z</date>
			<key>Date Added</key><date>2018-04-09T14:48:31Z</date>
			<key>Bit Rate</key><integer>128</integer>
			<key>Sample Rate</key><integer>44100</integer>
			<key>Artwork Count</key><integer>1</integer>
			<key>Persistent ID</key><string>71CE6FB32E298B71</string>
			<key>Track Type</key><string>File</string>
			<key>File Folder Count</key><integer>-1</integer>
			<key>Library Folder Count</key><integer>-1</integer>
			<key>Name</key><string>Beer</string>
			<key>Artist</key><string>Reel Big Fish</string>
			<key>Album Artist</key><string>Reel Big Fish</string>
			<key>Composer</key><string>Aaron Barrett/Adam Polakoff/Robert Quimby</string>
			<key>Album</key><string>Turn the Radio Off</string>
			<key>Genre</key><string>Ska</string>
			<key>Kind</key><string>MPEG audio file</string>
			<key>Comments</key><string>1</string>
			<key>Location</key><string>file:///Users/tonyfischetti/Dropbox/music/Reel%20Big%20Fish/Turn%20the%20Radio%20Off/06%20Beer.mp3</string>
		</dict>
		<key>43438</key>
		<dict>
			<key>Track ID</key><integer>43438</integer>
			<key>Size</key><integer>3030750</integer>
			<key>Total Time</key><integer>185756</integer>
			<key>Track Number</key><integer>4</integer>
			<key>Year</key><integer>1996</integer>
			<key>Date Modified</key><date>2019-12-30T04:20:30Z</date>
			<key>Date Added</key><date>2018-04-09T14:48:31Z</date>
			<key>Bit Rate</key><integer>128</integer>
			<key>Sample Rate</key><integer>44100</integer>
			<key>Artwork Count</key><integer>1</integer>
			<key>Persistent ID</key><string>B86C01728A50356A</string>
			<key>Track Type</key><string>File</string>
			<key>File Folder Count</key><integer>-1</integer>
			<key>Library Folder Count</key><integer>-1</integer>
			<key>Name</key><string>She Has a Girlfriend Now</string>
			<key>Artist</key><string>Reel Big Fish</string>
			<key>Album Artist</key><string>Reel Big Fish</string>
			<key>Composer</key><string>Aaron Barrett/Scott Klopfenstein</string>
			<key>Album</key><string>Turn the Radio Off</string>
			<key>Genre</key><string>Ska</string>
			<key>Kind</key><string>MPEG audio file</string>
			<key>Comments</key><string>1</string>
			<key>Location</key><string>file:///Users/tonyfischetti/Dropbox/music/Reel%20Big%20Fish/Turn%20the%20Radio%20Off/04%20She%20Has%20a%20Girlfriend%20Now.mp3</string>
		</dict>
		<key>43432</key>
		<dict>
			<key>Track ID</key><integer>43432</integer>
			<key>Size</key><integer>3703649</integer>
			<key>Total Time</key><integer>227552</integer>
			<key>Track Number</key><integer>1</integer>
			<key>Year</key><integer>1996</integer>
			<key>Date Modified</key><date>2019-12-30T04:20:30Z</date>
			<key>Date Added</key><date>2018-04-09T14:48:31Z</date>
			<key>Bit Rate</key><integer>128</integer>
			<key>Sample Rate</key><integer>44100</integer>
			<key>Artwork Count</key><integer>1</integer>
			<key>Persistent ID</key><string>5331FAA4D4B96F37</string>
			<key>Track Type</key><string>File</string>
			<key>File Folder Count</key><integer>-1</integer>
			<key>Library Folder Count</key><integer>-1</integer>
			<key>Name</key><string>Sell Out</string>
			<key>Artist</key><string>Reel Big Fish</string>
			<key>Album Artist</key><string>Reel Big Fish</string>
			<key>Composer</key><string>Aaron Barrett/Scott Klopfenstein</string>
			<key>Album</key><string>Turn the Radio Off</string>
			<key>Genre</key><string>Ska</string>
			<key>Kind</key><string>MPEG audio file</string>
			<key>Comments</key><string>1</string>
			<key>Location</key><string>file:///Users/tonyfischetti/Dropbox/music/Reel%20Big%20Fish/Turn%20the%20Radio%20Off/01%20Sell%20Out.mp3</string>
		</dict>
		<key>43450</key>
		<dict>
			<key>Track ID</key><integer>43450</integer>
			<key>Size</key><integer>3043172</integer>
			<key>Total Time</key><integer>185913</integer>
			<key>Track Number</key><integer>3</integer>
			<key>Date Modified</key><date>2019-12-30T04:20:41Z</date>
			<key>Date Added</key><date>2018-04-09T14:48:31Z</date>
			<key>Bit Rate</key><integer>128</integer>
			<key>Sample Rate</key><integer>44100</integer>
			<key>Artwork Count</key><integer>1</integer>
			<key>Persistent ID</key><string>CEF67E893C8E0E47</string>
			<key>Track Type</key><string>File</string>
			<key>File Folder Count</key><integer>-1</integer>
			<key>Library Folder Count</key><integer>-1</integer>
			<key>Name</key><string>She's Famous Now</string>
			<key>Artist</key><string>Reel Big Fish</string>
			<key>Album</key><string>Why Do They Rock So Hard?</string>
			<key>Genre</key><string>Ska</string>
			<key>Kind</key><string>MPEG audio file</string>
			<key>Comments</key><string>Leeched from Johny since 11/01</string>
			<key>Location</key><string>file:///Users/tonyfischetti/Dropbox/music/Reel%20Big%20Fish/Why%20Do%20They%20Rock%20So%20Hard_/03%20She's%20Famous%20Now.mp3</string>
		</dict>
		<key>43458</key>
		<dict>
			<key>Track ID</key><integer>43458</integer>
			<key>Size</key><integer>2652891</integer>
			<key>Total Time</key><integer>161671</integer>
			<key>Track Number</key><integer>6</integer>
			<key>Date Modified</key><date>2019-12-30T04:20:41Z</date>
			<key>Date Added</key><date>2018-04-09T14:48:31Z</date>
			<key>Bit Rate</key><integer>128</integer>
			<key>Sample Rate</key><integer>44100</integer>
			<key>Artwork Count</key><integer>1</integer>
			<key>Persistent ID</key><string>897F764DF3950F63</string>
			<key>Track Type</key><string>File</string>
			<key>File Folder Count</key><integer>-1</integer>
			<key>Library Folder Count</key><integer>-1</integer>
			<key>Name</key><string>Thank You for Not Moshing</string>
			<key>Artist</key><string>Reel Big Fish</string>
			<key>Album</key><string>Why Do They Rock So Hard?</string>
			<key>Genre</key><string>Ska</string>
			<key>Kind</key><string>MPEG audio file</string>
			<key>Comments</key><string>Leeched from Johny since 11/01</string>
			<key>Location</key><string>file:///Users/tonyfischetti/Dropbox/music/Reel%20Big%20Fish/Why%20Do%20They%20Rock%20So%20Hard_/06%20Thank%20You%20for%20Not%20Moshing.mp3</string>
		</dict>
		<key>50518</key>
		<dict>
			<key>Track ID</key><integer>50518</integer>
			<key>Size</key><integer>4037557</integer>
			<key>Total Time</key><integer>192156</integer>
			<key>Disc Number</key><integer>1</integer>
			<key>Disc Count</key><integer>1</integer>
			<key>Track Number</key><integer>3</integer>
			<key>Track Count</key><integer>15</integer>
			<key>Year</key><integer>1999</integer>
			<key>Date Modified</key><date>2019-12-29T16:27:23Z</date>
			<key>Date Added</key><date>2018-04-09T14:48:31Z</date>
			<key>Bit Rate</key><integer>160</integer>
			<key>Sample Rate</key><integer>44100</integer>
			<key>Artwork Count</key><integer>1</integer>
			<key>Persistent ID</key><string>3E9FACB8EC05AB1D</string>
			<key>Track Type</key><string>File</string>
			<key>File Folder Count</key><integer>-1</integer>
			<key>Library Folder Count</key><integer>-1</integer>
			<key>Name</key><string>Turning Japanese</string>
			<key>Artist</key><string>Skankin' Pickle</string>
			<key>Album</key><string>Sing Along With Skankin' Pickle</string>
			<key>Genre</key><string>Ska</string>
			<key>Kind</key><string>MPEG audio file</string>
			<key>Location</key><string>file:///Users/tonyfischetti/Dropbox/music/Skankin'%20Pickle/Sing%20Along%20With%20Skankin'%20Pickle/03%20Turning%20Japanese.mp3</string>
		</dict>
		<key>52274</key>
		<dict>
			<key>Track ID</key><integer>52274</integer>
			<key>Size</key><integer>5099359</integer>
			<key>Total Time</key><integer>210050</integer>
			<key>Disc Number</key><integer>1</integer>
			<key>Disc Count</key><integer>1</integer>
			<key>Track Number</key><integer>1</integer>
			<key>Year</key><integer>2003</integer>
			<key>Date Modified</key><date>2013-10-19T05:02:58Z</date>
			<key>Date Added</key><date>2018-04-09T14:48:31Z</date>
			<key>Bit Rate</key><integer>192</integer>
			<key>Sample Rate</key><integer>44100</integer>
			<key>Release Date</key><date>2003-08-26T12:00:00Z</date>
			<key>Artwork Count</key><integer>1</integer>
			<key>Persistent ID</key><string>A37E489C667B2B60</string>
			<key>Track Type</key><string>File</string>
			<key>File Folder Count</key><integer>5</integer>
			<key>Library Folder Count</key><integer>1</integer>
			<key>Name</key><string>Everything Went Numb</string>
			<key>Artist</key><string>Streetlight Manifesto</string>
			<key>Album</key><string>Everything Goes Numb</string>
			<key>Genre</key><string>Ska</string>
			<key>Kind</key><string>MPEG audio file</string>
			<key>Sort Artist</key><string>Streetlight Manifesto</string>
			<key>Location</key><string>file:///Users/tonyfischetti/Music/iTunes/iTunes%20Media/Music/Streetlight%20Manifesto/Everything%20Goes%20Numb/01%20Everything%20Went%20Numb.mp3</string>
		</dict>
		<key>52254</key>
		<dict>
			<key>Track ID</key><integer>52254</integer>
			<key>Size</key><integer>7945237</integer>
			<key>Total Time</key><integer>328698</integer>
			<key>Disc Number</key><integer>1</integer>
			<key>Disc Count</key><integer>1</integer>
			<key>Track Number</key><integer>7</integer>
			<key>Year</key><integer>2003</integer>
			<key>Date Modified</key><date>2013-10-19T05:03:00Z</date>
			<key>Date Added</key><date>2018-04-09T14:48:31Z</date>
			<key>Bit Rate</key><integer>192</integer>
			<key>Sample Rate</key><integer>44100</integer>
			<key>Artwork Count</key><integer>1</integer>
			<key>Persistent ID</key><string>67B630EA763391C4</string>
			<key>Track Type</key><string>File</string>
			<key>File Folder Count</key><integer>5</integer>
			<key>Library Folder Count</key><integer>1</integer>
			<key>Name</key><string>Failing, Flailing</string>
			<key>Artist</key><string>Streetlight Manifesto</string>
			<key>Album</key><string>Everything Goes Numb</string>
			<key>Genre</key><string>Ska</string>
			<key>Kind</key><string>MPEG audio file</string>
			<key>Sort Artist</key><string>Streetlight Manifesto</string>
			<key>Location</key><string>file:///Users/tonyfischetti/Music/iTunes/iTunes%20Media/Music/Streetlight%20Manifesto/Everything%20Goes%20Numb/07%20Failing,%20Flailing.mp3</string>
		</dict>
		<key>52266</key>
		<dict>
			<key>Track ID</key><integer>52266</integer>
			<key>Size</key><integer>6815490</integer>
			<key>Total Time</key><integer>281626</integer>
			<key>Disc Number</key><integer>1</integer>
			<key>Disc Count</key><integer>1</integer>
			<key>Track Number</key><integer>8</integer>
			<key>Year</key><integer>2003</integer>
			<key>Date Modified</key><date>2013-10-19T05:03:01Z</date>
			<key>Date Added</key><date>2018-04-09T14:48:31Z</date>
			<key>Bit Rate</key><integer>192</integer>
			<key>Sample Rate</key><integer>44100</integer>
			<key>Artwork Count</key><integer>1</integer>
			<key>Persistent ID</key><string>B6F367CEA20FDA34</string>
			<key>Track Type</key><string>File</string>
			<key>File Folder Count</key><integer>5</integer>
			<key>Library Folder Count</key><integer>1</integer>
			<key>Name</key><string>Here's to Life</string>
			<key>Artist</key><string>Streetlight Manifesto</string>
			<key>Album</key><string>Everything Goes Numb</string>
			<key>Genre</key><string>Ska</string>
			<key>Kind</key><string>MPEG audio file</string>
			<key>Sort Artist</key><string>Streetlight Manifesto</string>
			<key>Location</key><string>file:///Users/tonyfischetti/Music/iTunes/iTunes%20Media/Music/Streetlight%20Manifesto/Everything%20Goes%20Numb/08%20Here's%20to%20Life.mp3</string>
		</dict>
		<key>52272</key>
		<dict>
			<key>Track ID</key><integer>52272</integer>
			<key>Size</key><integer>4830597</integer>
			<key>Total Time</key><integer>198817</integer>
			<key>Disc Number</key><integer>1</integer>
			<key>Disc Count</key><integer>1</integer>
			<key>Track Number</key><integer>11</integer>
			<key>Year</key><integer>2003</integer>
			<key>Date Modified</key><date>2013-10-19T05:03:01Z</date>
			<key>Date Added</key><date>2018-04-09T14:48:31Z</date>
			<key>Bit Rate</key><integer>192</integer>
			<key>Sample Rate</key><integer>44100</integer>
			<key>Release Date</key><date>2003-08-26T12:00:00Z</date>
			<key>Artwork Count</key><integer>1</integer>
			<key>Persistent ID</key><string>A39B3BA19115907C</string>
			<key>Track Type</key><string>File</string>
			<key>File Folder Count</key><integer>5</integer>
			<key>Library Folder Count</key><integer>1</integer>
			<key>Name</key><string>The Saddest Song</string>
			<key>Artist</key><string>Streetlight Manifesto</string>
			<key>Album Artist</key><string>Streetlight Manifesto</string>
			<key>Composer</key><string>Tomas Kalnoky</string>
			<key>Album</key><string>Everything Goes Numb</string>
			<key>Genre</key><string>Ska</string>
			<key>Kind</key><string>MPEG audio file</string>
			<key>Sort Name</key><string>Saddest Song</string>
			<key>Sort Artist</key><string>Streetlight Manifesto</string>
			<key>Location</key><string>file:///Users/tonyfischetti/Music/iTunes/iTunes%20Media/Music/Streetlight%20Manifesto/Everything%20Goes%20Numb/11%20The%20Saddest%20Song.mp3</string>
		</dict>
		<key>52322</key>
		<dict>
			<key>Track ID</key><integer>52322</integer>
			<key>Size</key><integer>6252813</integer>
			<key>Total Time</key><integer>305423</integer>
			<key>Track Number</key><integer>2</integer>
			<key>Track Count</key><integer>10</integer>
			<key>Date Modified</key><date>2019-12-29T16:15:10Z</date>
			<key>Date Added</key><date>2018-04-09T14:48:31Z</date>
			<key>Bit Rate</key><integer>160</integer>
			<key>Sample Rate</key><integer>44100</integer>
			<key>Artwork Count</key><integer>1</integer>
			<key>Persistent ID</key><string>4A08787A1042A44B</string>
			<key>Track Type</key><string>File</string>
			<key>File Folder Count</key><integer>-1</integer>
			<key>Library Folder Count</key><integer>-1</integer>
			<key>Name</key><string>Down, Down, Down To Mephisto's Cafe</string>
			<key>Artist</key><string>Streetlight Manifesto</string>
			<key>Album</key><string>Somewhere in the Between</string>
			<key>Genre</key><string>Ska</string>
			<key>Kind</key><string>MPEG audio file</string>
			<key>Location</key><string>file:///Users/tonyfischetti/Dropbox/music/Streetlight%20Manifesto/Somewhere%20in%20the%20Between/02%20Down,%20Down,%20Down%20To%20Mephisto's%20Cafe.mp3</string>
		</dict>
		<key>52316</key>
		<dict>
			<key>Track ID</key><integer>52316</integer>
			<key>Size</key><integer>7788043</integer>
			<key>Total Time</key><integer>318484</integer>
			<key>Track Number</key><integer>9</integer>
			<key>Track Count</key><integer>10</integer>
			<key>Date Modified</key><date>2019-12-29T16:15:11Z</date>
			<key>Date Added</key><date>2018-04-09T14:48:31Z</date>
			<key>Bit Rate</key><integer>192</integer>
			<key>Sample Rate</key><integer>44100</integer>
			<key>Artwork Count</key><integer>1</integer>
			<key>Persistent ID</key><string>8144A5504CEA23D3</string>
			<key>Track Type</key><string>File</string>
			<key>File Folder Count</key><integer>-1</integer>
			<key>Library Folder Count</key><integer>-1</integer>
			<key>Name</key><string>The Receiving End Of It All</string>
			<key>Artist</key><string>Streetlight Manifesto</string>
			<key>Album</key><string>Somewhere in the Between</string>
			<key>Genre</key><string>Ska</string>
			<key>Kind</key><string>MPEG audio file</string>
			<key>Sort Name</key><string>Receiving End Of It All</string>
			<key>Location</key><string>file:///Users/tonyfischetti/Dropbox/music/Streetlight%20Manifesto/Somewhere%20in%20the%20Between/09%20The%20Receiving%20End%20Of%20It%20All.mp3</string>
		</dict>
		<key>7376</key>
		<dict>
			<key>Track ID</key><integer>7376</integer>
			<key>Size</key><integer>7711445</integer>
			<key>Total Time</key><integer>316891</integer>
			<key>Track Number</key><integer>2</integer>
			<key>Date Modified</key><date>2019-12-29T16:20:39Z</date>
			<key>Date Added</key><date>2018-04-09T14:48:31Z</date>
			<key>Bit Rate</key><integer>191</integer>
			<key>Sample Rate</key><integer>44100</integer>
			<key>Artwork Count</key><integer>1</integer>
			<key>Persistent ID</key><string>EB30A697C3C23762</string>
			<key>Track Type</key><string>File</string>
			<key>File Folder Count</key><integer>-1</integer>
			<key>Library Folder Count</key><integer>-1</integer>
			<key>Name</key><string>Shocker</string>
			<key>Artist</key><string>The Toasters</string>
			<key>Album</key><string>In Retrospect</string>
			<key>Genre</key><string>Ska</string>
			<key>Kind</key><string>MPEG audio file</string>
			<key>Sort Artist</key><string>Toasters</string>
			<key>Location</key><string>file:///Users/tonyfischetti/Dropbox/music/The%20Toasters/In%20Retrospect/02%20Shocker.mp3</string>
		</dict>
		<key>7340</key>
		<dict>
			<key>Track ID</key><integer>7340</integer>
			<key>Size</key><integer>4157262</integer>
			<key>Total Time</key><integer>168724</integer>
			<key>Track Number</key><integer>4</integer>
			<key>Date Modified</key><date>2019-12-29T16:20:40Z</date>
			<key>Date Added</key><date>2018-04-09T14:48:31Z</date>
			<key>Bit Rate</key><integer>192</integer>
			<key>Sample Rate</key><integer>44100</integer>
			<key>Artwork Count</key><integer>1</integer>
			<key>Persistent ID</key><string>9192397159A8D297</string>
			<key>Track Type</key><string>File</string>
			<key>File Folder Count</key><integer>-1</integer>
			<key>Library Folder Count</key><integer>-1</integer>
			<key>Name</key><string>Don't Let The Bastards Grind You Down</string>
			<key>Artist</key><string>The Toasters</string>
			<key>Album</key><string>In Retrospect</string>
			<key>Genre</key><string>Ska</string>
			<key>Kind</key><string>MPEG audio file</string>
			<key>Comments</key><string>Comment</string>
			<key>Sort Artist</key><string>Toasters</string>
			<key>Location</key><string>file:///Users/tonyfischetti/Dropbox/music/The%20Toasters/In%20Retrospect/04%20Don't%20Let%20The%20Bastards%20Grind%20You%20Down.mp3</string>
		</dict>
		<key>50126</key>
		<dict>
			<key>Track ID</key><integer>50126</integer>
			<key>Size</key><integer>3756337</integer>
			<key>Total Time</key><integer>156421</integer>
			<key>Track Number</key><integer>12</integer>
			<key>Year</key><integer>1999</integer>
			<key>Date Modified</key><date>2013-10-19T04:06:02Z</date>
			<key>Date Added</key><date>2018-04-09T14:48:31Z</date>
			<key>Bit Rate</key><integer>192</integer>
			<key>Sample Rate</key><integer>44100</integer>
			<key>Persistent ID</key><string>3F8D793A6595E20F</string>
			<key>Track Type</key><string>File</string>
			<key>File Folder Count</key><integer>5</integer>
			<key>Library Folder Count</key><integer>1</integer>
			<key>Name</key><string>Dirt Lip</string>
			<key>Artist</key><string>Big D and the Kids Table</string>
			<key>Album</key><string>Good Luck </string>
			<key>Genre</key><string>Ska</string>
			<key>Kind</key><string>MPEG audio file</string>
			<key>Comments</key><string>Pookman</string>
			<key>Location</key><string>file:///Users/tonyfischetti/Music/iTunes/iTunes%20Media/Music/Big%20D%20and%20the%20Kids%20Table/Good%20Luck/12%20Dirt%20Lip.mp3</string>
		</dict>
		<key>50020</key>
		<dict>
			<key>Track ID</key><integer>50020</integer>
			<key>Size</key><integer>4348116</integer>
			<key>Total Time</key><integer>180532</integer>
			<key>Track Number</key><integer>2</integer>
			<key>Track Count</key><integer>10</integer>
			<key>Year</key><integer>2002</integer>
			<key>Date Modified</key><date>2013-10-19T04:06:15Z</date>
			<key>Date Added</key><date>2018-04-09T14:48:31Z</date>
			<key>Bit Rate</key><integer>192</integer>
			<key>Sample Rate</key><integer>44100</integer>
			<key>Release Date</key><date>2002-01-01T12:00:00Z</date>
			<key>Artwork Count</key><integer>1</integer>
			<key>Persistent ID</key><string>EF57CD70C4BAAE56</string>
			<key>Track Type</key><string>File</string>
			<key>File Folder Count</key><integer>5</integer>
			<key>Library Folder Count</key><integer>1</integer>
			<key>Name</key><string>Evil Girl/Angry Girl</string>
			<key>Artist</key><string>Big D and the Kids Table</string>
			<key>Album</key><string>The Gipsy Hill</string>
			<key>Genre</key><string>Ska</string>
			<key>Kind</key><string>MPEG audio file</string>
			<key>Sort Album</key><string>Gipsy Hill</string>
			<key>Sort Artist</key><string>Big D and the Kids Table</string>
			<key>Location</key><string>file:///Users/tonyfischetti/Music/iTunes/iTunes%20Media/Music/Big%20D%20and%20the%20Kids%20Table/The%20Gipsy%20Hill/02%20Evil%20Girl_Angry%20Girl.mp3</string>
		</dict>
	</dict>
	<key>Playlists</key>
	<array>
		<dict>
			<key>Playlist ID</key><integer>138580</integer>
			<key>Playlist Persistent ID</key><string>AAB4951292F643FC</string>
			<key>All Items</key><true/>
			<key>Name</key><string>Ska</string>
			<key>Playlist Items</key>
			<array>
				<dict>
					<key>Track ID</key><integer>12328</integer>
				</dict>
				<dict>
					<key>Track ID</key><integer>12330</integer>
				</dict>
				<dict>
					<key>Track ID</key><integer>13580</integer>
				</dict>
				<dict>
					<key>Track ID</key><integer>13572</integer>
				</dict>
				<dict>
					<key>Track ID</key><integer>13556</integer>
				</dict>
				<dict>
					<key>Track ID</key><integer>13564</integer>
				</dict>
				<dict>
					<key>Track ID</key><integer>13576</integer>
				</dict>
				<dict>
					<key>Track ID</key><integer>7092</integer>
				</dict>
				<dict>
					<key>Track ID</key><integer>50924</integer>
				</dict>
				<dict>
					<key>Track ID</key><integer>50928</integer>
				</dict>
				<dict>
					<key>Track ID</key><integer>50940</integer>
				</dict>
				<dict>
					<key>Track ID</key><integer>51002</integer>
				</dict>
				<dict>
					<key>Track ID</key><integer>50830</integer>
				</dict>
				<dict>
					<key>Track ID</key><integer>50838</integer>
				</dict>
				<dict>
					<key>Track ID</key><integer>44140</integer>
				</dict>
				<dict>
					<key>Track ID</key><integer>44152</integer>
				</dict>
				<dict>
					<key>Track ID</key><integer>44154</integer>
				</dict>
				<dict>
					<key>Track ID</key><integer>44202</integer>
				</dict>
				<dict>
					<key>Track ID</key><integer>44210</integer>
				</dict>
				<dict>
					<key>Track ID</key><integer>43430</integer>
				</dict>
				<dict>
					<key>Track ID</key><integer>43438</integer>
				</dict>
				<dict>
					<key>Track ID</key><integer>43432</integer>
				</dict>
				<dict>
					<key>Track ID</key><integer>43450</integer>
				</dict>
				<dict>
					<key>Track ID</key><integer>43458</integer>
				</dict>
				<dict>
					<key>Track ID</key><integer>50518</integer>
				</dict>
				<dict>
					<key>Track ID</key><integer>52274</integer>
				</dict>
				<dict>
					<key>Track ID</key><integer>52254</integer>
				</dict>
				<dict>
					<key>Track ID</key><integer>52266</integer>
				</dict>
				<dict>
					<key>Track ID</key><integer>52272</integer>
				</dict>
				<dict>
					<key>Track ID</key><integer>52322</integer>
				</dict>
				<dict>
					<key>Track ID</key><integer>52316</integer>
				</dict>
				<dict>
					<key>Track ID</key><integer>7376</integer>
				</dict>
				<dict>
					<key>Track ID</key><integer>7340</integer>
				</dict>
				<dict>
					<key>Track ID</key><integer>50126</integer>
				</dict>
				<dict>
					<key>Track ID</key><integer>50020</integer>
				</dict>
			</array>
		</dict>
	</array>
</dict>
</plist>